{
    "consulqa2": {
        "0-consul-footer": {
            "content": "933f0db3ff35100ac5074e359b807d0f",
            "lastUpdate": "2018-07-12T19:17:56.818Z"
        },
        "0-consul-head-content": {
            "content": "7851ded5f4368f8710c34ca86f617440",
            "lastUpdate": "2018-07-12T19:17:56.820Z"
        },
        "0-consul-header-landing-aniversario": {
            "content": "0a1034578528692c332dbb04da134a2f",
            "lastUpdate": "2018-07-12T18:41:19.288Z"
        },
        "0-consul-header": {
            "content": "4d0f4b30c9e75c14ab8c8c75af806004",
            "lastUpdate": "2018-07-12T18:41:19.289Z"
        },
        "0-consul-servicos": {
            "content": "cd9055be1a994e6353213406e334dd5d",
            "lastUpdate": "2018-07-12T18:41:19.290Z"
        },
        "0-consul-top-header": {
            "content": "120689e9fbea4c63ed70a0a4eaa5106b",
            "lastUpdate": "2018-07-12T18:41:19.292Z"
        },
        "0-consul-busca-chaordic": {
            "content": "c551def5c9ca4119d8cdd4604840109b",
            "lastUpdate": "2018-07-12T19:17:58.902Z"
        },
        "0-consul-busca-chaordic2": {
            "content": "847bfe5719884451fc19d3331b222677",
            "lastUpdate": "2018-07-12T19:17:58.903Z"
        },
        "0-consul-busca": {
            "content": "7be03d9a64a4f260e3c7628d3b7dee30",
            "lastUpdate": "2018-07-12T19:17:58.905Z"
        },
        "0-consul-calculadora-btu": {
            "content": "bacaae85862d3a35b7fa45b95e63fdb3",
            "lastUpdate": "2018-07-12T19:17:58.906Z"
        },
        "0-consul-home-chaordic": {
            "content": "9d201ba4dc3307acd1e65be832c88e05",
            "lastUpdate": "2018-07-12T18:41:21.495Z"
        },
        "0-consul-home-pj": {
            "content": "7ee9433150aa5d6f3a744dd41c6a7584",
            "lastUpdate": "2018-07-12T19:17:58.908Z"
        },
        "0-consul-home": {
            "content": "bc1d37ea593a23296edae3797f6a2103",
            "lastUpdate": "2018-07-12T19:17:58.909Z"
        },
        "0-consul-institucional": {
            "content": "9d9d5644831691b9d3474678dbb57478",
            "lastUpdate": "2018-07-12T19:17:58.910Z"
        },
        "0-consul-listagem-ar-condicionado": {
            "content": "a49eb321f41adb1d9b152d8ca2447ad5",
            "lastUpdate": "2018-07-12T19:17:58.918Z"
        },
        "0-consul-listagem": {
            "content": "21276964f9a27d82b50d6716976d62b7",
            "lastUpdate": "2018-07-12T19:17:58.920Z"
        },
        "0-consul-login": {
            "content": "dc122725f132e102a7d4252df0f09425",
            "lastUpdate": "2018-07-12T19:17:58.921Z"
        },
        "0-consul-meuspedidos": {
            "content": "511c7257603a035b01f2b74dc738375e",
            "lastUpdate": "2018-07-12T19:17:58.927Z"
        },
        "0-consul-minhaconta": {
            "content": "eb011f2dca27792ccf12d3c2f49e3607",
            "lastUpdate": "2018-07-12T19:17:58.928Z"
        },
        "0-consul-minicart": {
            "content": "9a64cdaf2de672b917e58e378eccc313",
            "lastUpdate": "2018-07-12T18:41:21.520Z"
        },
        "0-consul-neemu": {
            "content": "e64aee3b4aaa820ab1342a522976f645",
            "lastUpdate": "2018-07-12T19:17:58.929Z"
        },
        "0-consul-pedidos": {
            "content": "7e3894befee3fffd0d71954dcdc6bb42",
            "lastUpdate": "2018-07-12T19:17:58.930Z"
        },
        "0-consul-produto-quiz": {
            "content": "765c698741b814d5a406d310f2417b29",
            "lastUpdate": "2018-07-12T19:17:58.933Z"
        },
        "0-consul-produto": {
            "content": "559b3677357d53c79e8238a8747e3b8d",
            "lastUpdate": "2018-07-12T19:17:58.935Z"
        },
        "0-consul-destaque": {
            "content": "2e36eb7a4635fc7848217c6e0a00a4b9",
            "lastUpdate": "2018-07-12T19:08:08.609Z"
        },
        "0-prateleira-default": {
            "content": "09a08ff21849189d597194c6e7e722e0",
            "lastUpdate": "2018-07-12T19:08:08.612Z"
        },
        "0-prateleira-upsell-cns": {
            "content": "d95eeddf4c88c6d13f286fd615005652",
            "lastUpdate": "2018-07-12T19:08:08.614Z"
        },
        "0-consul-compare": {
            "content": "7573983090d0276aa2fe8afeda12a801",
            "lastUpdate": "2018-07-12T19:17:58.907Z"
        },
        "0-consul-landing-birthday-2018-v2": {
            "content": "ffe73de37d0c9244c5a5121a89730dd0",
            "lastUpdate": "2018-07-12T19:17:58.911Z"
        },
        "0-consul-landing-birthday-2018": {
            "content": "5dd1ce1ee4c892565302a9266a3c8c20",
            "lastUpdate": "2018-07-12T19:17:58.912Z"
        },
        "0-consul-landing-concurso": {
            "content": "a17dbcb69ecb7cd8ff031f5d27ed8be5",
            "lastUpdate": "2018-07-12T19:17:58.913Z"
        },
        "0-consul-landing-de-combos": {
            "content": "b5fcb62b65d9cee99de91a0a606ce814",
            "lastUpdate": "2018-07-12T19:17:58.915Z"
        },
        "0-consul-landing-gae-compra-interno": {
            "content": "e38731c6aa4d695a294027a260bd4951",
            "lastUpdate": "2018-07-12T19:17:58.916Z"
        },
        "0-consul-landing-gae": {
            "content": "ec959cc6ec764cee6bb60ae37ccc676b",
            "lastUpdate": "2018-07-12T19:17:58.917Z"
        },
        "0-consul-pre-home": {
            "content": "606409189878b44a88d9b61f3aa5bc23",
            "lastUpdate": "2018-07-12T19:17:58.931Z"
        },
        "0-consul-produto-calc": {
            "content": "a4e50c0a228f6ea763b273a0f94cb947",
            "lastUpdate": "2018-07-12T19:17:58.932Z"
        },
        "0-consul-smart-beer-QuickView": {
            "content": "56fa58cc09818e832b89431221b8fb21",
            "lastUpdate": "2018-07-12T19:17:58.936Z"
        },
        "0-consul-smart-beer": {
            "content": "25612f6edbffbc7ae48bcb39eacc58f0",
            "lastUpdate": "2018-07-12T19:17:58.937Z"
        },
        "consul-landing-wonderland": {
            "content": "447461aba77b359214cc41b9849cbbc8",
            "lastUpdate": "2018-07-12T19:17:58.938Z"
        }
    },
    "consul": {
        "0-consul-header-landing-aniversario": {
            "content": "0a1034578528692c332dbb04da134a2f",
            "lastUpdate": "2019-08-26T16:36:35.144Z"
        },
        "0-consul-servicos": {
            "content": "cd9055be1a994e6353213406e334dd5d",
            "lastUpdate": "2019-08-26T16:36:35.146Z"
        },
        "0-consul-top-header": {
            "content": "120689e9fbea4c63ed70a0a4eaa5106b",
            "lastUpdate": "2019-07-31T17:36:44.449Z"
        },
        "0-consul-busca-chaordic": {
            "content": "f405e7f30dd14519e40ded26daef426b",
            "lastUpdate": "2019-08-26T16:59:51.255Z"
        },
        "0-consul-busca-chaordic2": {
            "content": "8ec1d3554a552533fc5e45ddd42c4ea4",
            "lastUpdate": "2019-08-26T16:59:51.258Z"
        },
        "0-consul-busca": {
            "content": "09a8faf3e080ef4124a501d60f487baa",
            "lastUpdate": "2019-08-26T16:59:51.260Z"
        },
        "0-consul-calculadora-btu": {
            "content": "d5dc90f8a441baac8d6791df8efc52fd",
            "lastUpdate": "2019-08-26T16:59:51.263Z"
        },
        "0-consul-home-chaordic": {
            "content": "290133e6cb99daeddbb0a15f0645984e",
            "lastUpdate": "2019-07-10T20:51:14.442Z"
        },
        "0-consul-home-pj": {
            "content": "b229763b4b40fa2218f9e10b8190a155",
            "lastUpdate": "2019-08-26T16:59:51.269Z"
        },
        "0-consul-institucional": {
            "content": "d1999191a680538c9c1ebbab85ff12c7",
            "lastUpdate": "2019-08-26T16:59:51.275Z"
        },
        "0-consul-login": {
            "content": "e629f0c60d5c8444a57058c5e9794414",
            "lastUpdate": "2019-08-26T16:59:51.306Z"
        },
        "0-consul-meuspedidos": {
            "content": "f478ae63b0f7b74bca9cf91c6ccf4ff0",
            "lastUpdate": "2019-08-26T16:59:51.309Z"
        },
        "0-consul-minhaconta": {
            "content": "f1b6d619a720e0eb412d9c248fb66086",
            "lastUpdate": "2019-08-26T16:59:51.312Z"
        },
        "0-consul-minicart": {
            "content": "9a64cdaf2de672b917e58e378eccc313",
            "lastUpdate": "2019-08-26T16:36:38.900Z"
        },
        "0-consul-neemu": {
            "content": "46069106867740388e50405492dde00e",
            "lastUpdate": "2019-08-26T16:59:51.315Z"
        },
        "0-consul-pedidos": {
            "content": "f934b9f1d20fd3785c9935d544e374be",
            "lastUpdate": "2019-08-26T16:59:51.317Z"
        },
        "0-consul-produto-quiz": {
            "content": "7ba4cc367d9bacfecbbdad4ecba6990a",
            "lastUpdate": "2019-08-26T16:59:51.324Z"
        },
        "0-consul-produto": {
            "content": "4a422c4770a470eb782470d313d74186",
            "lastUpdate": "2019-08-26T16:59:51.331Z"
        },
        "0-consul-destaque": {
            "content": "eff9bc74812a84792144166a6aa4e3a7",
            "lastUpdate": "2019-07-10T20:51:17.439Z"
        },
        "0-prateleira-default": {
            "content": "17f1f376be70688eab02fcb07546d783",
            "lastUpdate": "2019-07-10T20:51:17.448Z"
        },
        "0-consul-compare": {
            "content": "89c331bd73d523154b37c1e46c9023e0",
            "lastUpdate": "2019-05-22T18:09:05.853Z"
        },
        "0-consul-landing-birthday-2018-v2": {
            "content": "e600b1ff8de4c8f0bfc4089515be04d4",
            "lastUpdate": "2019-05-22T18:09:05.868Z"
        },
        "0-consul-landing-birthday-2018": {
            "content": "0736aba9963da9aa34a8c9406ae51793",
            "lastUpdate": "2019-05-22T18:09:05.870Z"
        },
        "0-consul-landing-concurso": {
            "content": "a3d1fbc5efa867735f55de8e1198c029",
            "lastUpdate": "2019-05-22T18:09:05.873Z"
        },
        "0-consul-landing-de-combos": {
            "content": "2ad573165bf836bd74bec338410332ff",
            "lastUpdate": "2019-05-22T18:09:05.875Z"
        },
        "0-consul-landing-gae-compra-interno": {
            "content": "0c7379b6bf7a5f031267d53d3269b6be",
            "lastUpdate": "2019-05-22T18:09:05.883Z"
        },
        "0-consul-landing-gae": {
            "content": "533b74ef257266a2ce3e20dfcb23c622",
            "lastUpdate": "2019-05-22T18:09:05.886Z"
        },
        "0-consul-pre-home": {
            "content": "1e5702cb96efcb9cff11c6c929b1445e",
            "lastUpdate": "2019-05-22T18:09:05.910Z"
        },
        "0-consul-produto-calc": {
            "content": "18b4bebd5b7bb748adb04edae8ba0123",
            "lastUpdate": "2019-05-22T18:09:05.914Z"
        },
        "0-consul-smart-beer-QuickView": {
            "content": "9f21fc87fc0973b54a8b15e45c31cc14",
            "lastUpdate": "2019-05-22T18:09:05.924Z"
        },
        "0-consul-smart-beer": {
            "content": "f37406895469bae43c00e2bc9fdc5860",
            "lastUpdate": "2019-05-22T18:09:05.927Z"
        },
        "consul-landing-wonderland": {
            "content": "bb408ef1f33a699f376c2aca2a0afa55",
            "lastUpdate": "2019-05-22T18:09:05.937Z"
        },
        "files/checkout-confirmation-custom.js": {
            "content": "3816ed4afe5b26fb8ed373c80e4e96d4",
            "lastUpdate": "2019-08-26T16:59:43.964Z"
        },
        "files/checkout5-custom.js": {
            "content": "52e0e2cf8cba2ab6340bb23596c15fe0",
            "lastUpdate": "2019-08-26T16:59:43.969Z"
        },
        "arquivos/checkout-confirmation-custom.min.js": {
            "content": "3816ed4afe5b26fb8ed373c80e4e96d4",
            "lastUpdate": "2019-08-26T16:59:46.943Z"
        },
        "arquivos/checkout5-custom.css": {
            "content": "af3b2330badec509bead981d79105d5f",
            "lastUpdate": "2019-08-26T16:59:46.945Z"
        },
        "arquivos/checkout5-custom.min.js": {
            "content": "52e0e2cf8cba2ab6340bb23596c15fe0",
            "lastUpdate": "2019-08-26T16:59:46.948Z"
        },
        "arquivos/consul2-account.css": {
            "content": "a478bbea9acfa4f26a64628de1393ec5",
            "lastUpdate": "2019-04-12T15:25:43.277Z"
        },
        "arquivos/consul2-bf.css": {
            "content": "136530a7d1157a0604018e63f908a492",
            "lastUpdate": "2019-03-19T14:12:25.345Z"
        },
        "arquivos/consul2-home.css": {
            "content": "230bf953dce4b7e3277eb393bb2d12bf",
            "lastUpdate": "2019-08-26T16:59:46.958Z"
        },
        "arquivos/consul2-home.min.js": {
            "content": "411a734d2b5bf46e80b49082b92f9261",
            "lastUpdate": "2019-08-26T16:59:46.961Z"
        },
        "arquivos/consul2-institucional.css": {
            "content": "adb3810b4b9b4d7f8291003292b808c2",
            "lastUpdate": "2019-08-26T16:59:46.964Z"
        },
        "arquivos/consul2-login.css": {
            "content": "736f534cd2cafa7c1c3865276e00576f",
            "lastUpdate": "2019-08-26T16:59:46.971Z"
        },
        "arquivos/consul2-myorders.css": {
            "content": "5af444b10c611d1425a0df92471f917b",
            "lastUpdate": "2019-05-20T15:21:48.462Z"
        },
        "arquivos/consul2-myorders.min.js": {
            "content": "7a5e32fcace65b21fc0ce8a121acfd44",
            "lastUpdate": "2019-08-26T16:59:46.974Z"
        },
        "arquivos/consul2-produto.css": {
            "content": "1e60ce27ff3bdaa109b14aa32863b906",
            "lastUpdate": "2019-08-26T16:59:46.976Z"
        },
        "arquivos/consul2-produto.min.js": {
            "content": "2a0cdaf5b93c50d790441ea7faa36723",
            "lastUpdate": "2019-08-26T16:59:46.979Z"
        },
        "arquivos/consulcoheadline_std_bd-webfont.eot.css": {
            "content": "13b2a15696384e6546d1ebc17469be29",
            "lastUpdate": "2019-07-10T19:09:59.205Z"
        },
        "arquivos/consulcoheadline_std_bd-webfont.svg.css": {
            "content": "7c1edfcd005b803656a6ce5771639655",
            "lastUpdate": "2019-08-26T16:36:33.717Z"
        },
        "arquivos/consulcoheadline_std_bd-webfont.ttf.css": {
            "content": "5d20b3bf4856b474497772b93ca5edd4",
            "lastUpdate": "2019-07-10T19:09:59.209Z"
        },
        "arquivos/consulcoheadline_std_bd-webfont.woff.css": {
            "content": "a24fb1d6623e1a879bd6ce2410f8620c",
            "lastUpdate": "2019-07-10T19:09:59.211Z"
        },
        "arquivos/consulcoheadline_std_bd-webfont.woff2.css": {
            "content": "ebd6a9b6e9f949cea33b3765464afcc1",
            "lastUpdate": "2019-07-10T19:09:59.213Z"
        },
        "arquivos/consulcoheadline_std_lt-webfont.eot.css": {
            "content": "1d3accb3c60bf790aa55c45635d7ff5b",
            "lastUpdate": "2019-07-10T19:09:59.215Z"
        },
        "arquivos/consulcoheadline_std_lt-webfont.svg.css": {
            "content": "9310afe71921eccdec8f1c2295a40d6a",
            "lastUpdate": "2019-08-26T16:36:33.720Z"
        },
        "arquivos/consulcoheadline_std_lt-webfont.ttf.css": {
            "content": "0b5ea22ef1f79c158550b50e688ba445",
            "lastUpdate": "2019-07-10T19:09:59.220Z"
        },
        "arquivos/consulcoheadline_std_lt-webfont.woff.css": {
            "content": "bef9063956e6c10b072ee6d8c97281b6",
            "lastUpdate": "2019-07-10T19:09:59.223Z"
        },
        "arquivos/consulcoheadline_std_lt-webfont.woff2.css": {
            "content": "9917e5cbf336138d8aa0bfe3f364be5e",
            "lastUpdate": "2019-07-10T19:09:59.227Z"
        },
        "arquivos/consulcoheadline_std_rg-webfont.eot.css": {
            "content": "94a294365dcb7cbe4e1c54b39e384091",
            "lastUpdate": "2019-07-10T19:09:59.229Z"
        },
        "arquivos/consulcoheadline_std_rg-webfont.svg.css": {
            "content": "929f9f03b1b8023348e5990709d61a25",
            "lastUpdate": "2019-08-26T16:36:33.723Z"
        },
        "arquivos/consulcoheadline_std_rg-webfont.ttf.css": {
            "content": "b630c09e3ee56c6a0d05fa6bc4889b02",
            "lastUpdate": "2019-07-10T19:09:59.234Z"
        },
        "arquivos/consulcoheadline_std_rg-webfont.woff.css": {
            "content": "9bb77b94b823cbe8fbe3b7899d297e28",
            "lastUpdate": "2019-07-10T19:09:59.236Z"
        },
        "arquivos/consulcoheadline_std_rg-webfont.woff2.css": {
            "content": "179f798eb0d872074c48067d047f3dd5",
            "lastUpdate": "2019-07-10T19:09:59.239Z"
        },
        "arquivos/whirlpool2.eot.css": {
            "content": "af1e9544d9a341d4b882d3e6b9534fdc",
            "lastUpdate": "2019-07-10T19:09:59.242Z"
        },
        "arquivos/whirlpool2.svg.css": {
            "content": "f338b6a98422f3bca293f6aa1e6a3da5",
            "lastUpdate": "2019-08-26T16:36:33.727Z"
        },
        "arquivos/whirlpool2.ttf.css": {
            "content": "e7639a56979c74776fa35cd1bdc03968",
            "lastUpdate": "2019-07-10T19:09:59.246Z"
        },
        "arquivos/whirlpool2.woff.css": {
            "content": "3af078c9908279729c57b8ccf0fcb140",
            "lastUpdate": "2019-07-10T19:09:59.249Z"
        },
        "arquivos/whirlpool2.woff2.css": {
            "content": "e122b1e5d3abd6c496bdac0129e700df",
            "lastUpdate": "2019-07-10T19:09:59.251Z"
        },
        "arquivos/calculadora-btu.css": {
            "content": "9b1fa4d4b422dc8d0c0d16c3f76833e1",
            "lastUpdate": "2018-07-26T14:35:23.018Z"
        },
        "arquivos/calculadora-btu.min.js": {
            "content": "eafb18d1234b638f5b7606f77d41b559",
            "lastUpdate": "2019-05-22T17:52:36.481Z"
        },
        "arquivos/consul-landing-combos.css": {
            "content": "445e82f09a941138e5372306b68f077f",
            "lastUpdate": "2019-05-22T17:52:36.506Z"
        },
        "arquivos/consul-landing-combos.min.js": {
            "content": "1662ffcd4db0f2d3c9530807324e013a",
            "lastUpdate": "2019-05-22T17:52:36.508Z"
        },
        "arquivos/consul-landing-concurso.css": {
            "content": "65813ae3b9a3972e66aba10bc1cdc3ff",
            "lastUpdate": "2019-05-22T17:52:36.511Z"
        },
        "arquivos/consul-landing-concurso.min.js": {
            "content": "872de530b6b2bc2de8040c244af2f72a",
            "lastUpdate": "2019-05-22T17:52:36.513Z"
        },
        "arquivos/consul-landing-gae-2017.css": {
            "content": "c908384e657b0b0110240b8c6b071765",
            "lastUpdate": "2019-05-22T17:52:36.515Z"
        },
        "arquivos/consul-landing-gae-2017.min.js": {
            "content": "d367ff9b31f39160ec7f299ccd0367f7",
            "lastUpdate": "2019-05-22T17:52:36.517Z"
        },
        "arquivos/consul-landing-wonderland.css": {
            "content": "f758c15ffb77cdc51710f7d1f9cd7c2a",
            "lastUpdate": "2018-07-26T14:35:23.028Z"
        },
        "arquivos/consul-landing-wonderland.min.js": {
            "content": "27b4275da1517eb0ac6f40f5c47357f3",
            "lastUpdate": "2019-05-22T17:52:36.522Z"
        },
        "arquivos/consul2-comparador.css": {
            "content": "70fcd92c19a9200143cc00968d7a4032",
            "lastUpdate": "2019-05-22T17:52:36.528Z"
        },
        "arquivos/consul2-comparador.min.js": {
            "content": "bd2b9353e09e7942a58f5f43f753cd2a",
            "lastUpdate": "2019-05-22T17:52:36.530Z"
        },
        "arquivos/consul2-landing-gae-compra-interno.css": {
            "content": "1380bece80f4786f7b5351bebc75c516",
            "lastUpdate": "2019-05-22T17:52:36.558Z"
        },
        "arquivos/consul2-pre-home.css": {
            "content": "6befa2a5b5106c4fcc1ef51d19435a26",
            "lastUpdate": "2018-07-26T14:35:23.038Z"
        },
        "arquivos/landing-birthday-2018-2.css": {
            "content": "869e35e4ab629203ba77f773212caef8",
            "lastUpdate": "2019-05-22T17:52:36.594Z"
        },
        "arquivos/landing-birthday-2018-2.min.js": {
            "content": "7b81869caa386cef3bae628586e3f2c3",
            "lastUpdate": "2019-05-22T17:52:36.596Z"
        },
        "arquivos/landing-birthday-2018.css": {
            "content": "d3c3cff0e6a493e4d5177f6c2d3be77a",
            "lastUpdate": "2019-05-22T17:52:36.598Z"
        },
        "arquivos/landing-birthday-2018.min.js": {
            "content": "f6df72a95c7fdd922fa9c32ed9a72bfb",
            "lastUpdate": "2019-05-22T17:52:36.601Z"
        },
        "arquivos/quick-view-ted.css": {
            "content": "aff603003eb96f804c335487f2aba471",
            "lastUpdate": "2018-07-26T14:35:23.046Z"
        },
        "arquivos/simulador-lavadora.css": {
            "content": "de3f956913245983d112d0dc81fd4d67",
            "lastUpdate": "2018-07-26T14:35:23.047Z"
        },
        "arquivos/simulador-lavadora.min.js": {
            "content": "ffedd6c42925ae575daf0674b3c51747",
            "lastUpdate": "2019-05-22T17:52:36.608Z"
        },
        "arquivos/smart-beer-custom.min.js": {
            "content": "ac437381f4a6805618a76241c22b5a5f",
            "lastUpdate": "2019-05-22T17:52:36.610Z"
        },
        "arquivos/smart-beer.css": {
            "content": "1d9d4c87feb904f8f158d9dc900c0e15",
            "lastUpdate": "2018-07-26T14:35:23.050Z"
        },
        "arquivos/smart-beer.min.js": {
            "content": "54c7189990e3723a6c938ae1e1de2b62",
            "lastUpdate": "2019-05-22T17:52:36.613Z"
        },
        "files/checkout5-custom.css": {
            "content": "af3b2330badec509bead981d79105d5f",
            "lastUpdate": "2019-08-26T16:59:43.967Z"
        },
        "arquivos/cns-coupon.css": {
            "content": "ef04a5d0d9e3d8f8b57132656105747b",
            "lastUpdate": "2019-05-22T17:52:36.490Z"
        },
        "arquivos/cns-coupon.min.js": {
            "content": "44cb91126b54ebd821fdd6e0f9eaea5e",
            "lastUpdate": "2019-05-22T17:52:36.492Z"
        },
        "arquivos/cns-performance-page-blackfriday-2018.css": {
            "content": "ab9340813a560ae6f4f96ed5177d99f6",
            "lastUpdate": "2019-05-22T17:52:36.494Z"
        },
        "arquivos/cns-performance-page-blackfriday-2018.min.js": {
            "content": "64c78c86e573f665cd4fbf7e45fe8d0b",
            "lastUpdate": "2019-05-22T17:52:36.496Z"
        },
        "arquivos/consul-landing-blackfriday-2018.css": {
            "content": "0c9b1889774dfe264956c5e4c5c67de9",
            "lastUpdate": "2019-05-22T17:52:36.502Z"
        },
        "arquivos/consul-landing-blackfriday-2018.min.js": {
            "content": "09605283053438377fc2e0c50975fa38",
            "lastUpdate": "2019-05-22T17:52:36.504Z"
        },
        "arquivos/consul2-bf-2018.css": {
            "content": "751a8cc5c50c7cb7bf2758f3ee86f514",
            "lastUpdate": "2019-05-20T15:21:48.439Z"
        },
        "arquivos/consul2-coupon.css": {
            "content": "5681d7bc8c2b894d1fbb5e76fcf8a8d7",
            "lastUpdate": "2018-10-31T14:14:29.771Z"
        },
        "arquivos/consul2-cta.min.js": {
            "content": "7302f840bf2c831a25fa30eda37e2262",
            "lastUpdate": "2019-08-26T16:59:46.956Z"
        },
        "0-consul-coupon": {
            "content": "8e77fd53d8082ba72c70593fb5bfb881",
            "lastUpdate": "2019-05-22T18:09:05.856Z"
        },
        "0-consul-cta": {
            "content": "a002b0969eba9284c287612b9941da13",
            "lastUpdate": "2019-08-26T16:59:51.266Z"
        },
        "0-consul-landing-blackfriday-2018": {
            "content": "c47f7a28525ec40bbc0b5fb9fbbe789d",
            "lastUpdate": "2019-02-05T21:46:43.075Z"
        },
        "0-shelf-blackfriday-2018": {
            "content": "27658782b45d01f5cdd77121871f9332",
            "lastUpdate": "2019-08-26T16:36:41.255Z"
        },
        "0-consul-produto-refri": {
            "content": "5258dbd39e6ec754376a17e223a4222a",
            "lastUpdate": "2019-08-26T16:59:51.328Z"
        },
        "arquivos/consul2-app.min.js": {
            "content": "6f90616ce3394e924fd2950a68b71a41",
            "lastUpdate": "2019-08-26T16:59:46.950Z"
        },
        "arquivos/consul2-listagem.css": {
            "content": "6abcb340358cb1945032554f571819e0",
            "lastUpdate": "2019-08-26T16:59:46.966Z"
        },
        "arquivos/consul2-listagem.min.js": {
            "content": "649c45d6ac0f6217be0f0332d85c61d1",
            "lastUpdate": "2019-08-26T16:59:46.968Z"
        },
        "arquivos/consul2-style.css": {
            "content": "9e5e3d3e9e29ceca19badade14dbb99a",
            "lastUpdate": "2019-08-26T16:59:46.995Z"
        },
        "0-consul-footer": {
            "content": "033a10b78483f24b799f056bb5eeaebc",
            "lastUpdate": "2019-08-26T16:59:48.631Z"
        },
        "0-consul-head-content": {
            "content": "bd5a768c02682f6fdcd3b51df3c1b90a",
            "lastUpdate": "2019-08-26T16:59:48.632Z"
        },
        "0-consul-header": {
            "content": "1ca62a653c3475d1e6277dbb6ee8e44d",
            "lastUpdate": "2019-07-26T20:25:29.233Z"
        },
        "0-consul-home": {
            "content": "fb9f651236300356924591413590e1a9",
            "lastUpdate": "2019-08-26T16:59:51.272Z"
        },
        "0-consul-listagem-ar-condicionado": {
            "content": "d14877599d54308474d7e55049338aaa",
            "lastUpdate": "2019-08-26T16:59:51.297Z"
        },
        "0-consul-listagem": {
            "content": "0cc6c419f7a350111a7ed6b6f7724b19",
            "lastUpdate": "2019-08-26T16:59:51.303Z"
        },
        "arquivos/cozinha-ambientada.css": {
            "content": "1acd40a43f583587ba9e8ed61f6ad580",
            "lastUpdate": "2019-05-22T17:52:36.586Z"
        },
        "arquivos/cozinha-ambientada.min.js": {
            "content": "8ebba378c51bd0598e555c0de66c50b6",
            "lastUpdate": "2019-05-22T17:52:36.588Z"
        },
        "0-consul-cozinha-ambientada": {
            "content": "711ef2f2113a98f9a04f9cc1937efcbe",
            "lastUpdate": "2019-02-26T19:54:38.101Z"
        },
        "0-consul-prateleira-default": {
            "content": "2b20f992edcba3b9e17479556e483fdd",
            "lastUpdate": "2019-07-26T20:25:34.351Z"
        },
        "arquivos/consul2-fonts.css": {
            "content": "30af80459c5d644a3c0be84fef72246c",
            "lastUpdate": "2019-05-07T19:04:16.076Z"
        },
        "arquivos/consul2-icons.css": {
            "content": "e0d82e70c1b5bb9d2846201dd2529a99",
            "lastUpdate": "2019-04-12T15:25:43.290Z"
        },
        "arquivos/landing-gae-2019.min.js": {
            "content": "bf49f4d31e3cc804f29081dfb2d9cef3",
            "lastUpdate": "2019-05-22T17:52:36.604Z"
        },
        "0-consul-landing-gae-2019": {
            "content": "7e35b727cba0a9e783edc2c1becb4ac2",
            "lastUpdate": "2019-05-22T18:09:05.880Z"
        },
        "arquivos/landing-gae-2019.css": {
            "content": "aa85d3e6121335ab9545af5023e8d4f4",
            "lastUpdate": "2019-05-22T17:52:36.603Z"
        },
        "arquivos/consul-dia-das-maes.css": {
            "content": "89e16b9bc76f4661e713a61f15a7c339",
            "lastUpdate": "2019-05-22T17:52:36.498Z"
        },
        "arquivos/consul-dia-das-maes.min.js": {
            "content": "c4ff9fdc3e7a9411a292542b3ad46ca9",
            "lastUpdate": "2019-05-22T17:52:36.500Z"
        },
        "arquivos/custom-datalayer.min.js": {
            "content": "ba0d3870a411fe7c537dd86acdc52b0a",
            "lastUpdate": "2019-05-22T17:52:36.592Z"
        },
        "0-consul-landing-dia-das-maes": {
            "content": "16f51dad85f5313cacdfe6546c7509ef",
            "lastUpdate": "2019-05-22T18:09:05.878Z"
        },
        "arquivos/Rastreio.min.js": {
            "content": "1fe5c2035a96be017616aa06395f54b4",
            "lastUpdate": "2019-05-22T17:52:36.606Z"
        },
        "0-performance-page-blackfriday-2018": {
            "content": "be05fc6aded3026cf4825bf46483786b",
            "lastUpdate": "2019-05-22T18:09:05.931Z"
        },
        "0-Rastreio": {
            "content": "f74b1f64a4c3c06ceab49aad6383612a",
            "lastUpdate": "2019-05-22T18:09:05.934Z"
        },
        "0-consul-footer-2019-after": {
            "content": "9f100458fb671769ff84c13899e1136e",
            "lastUpdate": "2019-08-26T16:59:48.627Z"
        },
        "0-consul-footer-2019-atendimento": {
            "content": "1879b4ce64390f78b83312d99efa7c6f",
            "lastUpdate": "2019-07-10T20:51:11.630Z"
        },
        "0-consul-footer-2019-bottom": {
            "content": "5da9045db5f95954d1142b8345c152be",
            "lastUpdate": "2019-08-15T20:37:11.268Z"
        },
        "0-consul-footer-2019-menu": {
            "content": "bfd94f8e0ae4b88b3d302d52c282919a",
            "lastUpdate": "2019-07-10T20:51:11.636Z"
        },
        "0-consul-footer-2019-newsletter": {
            "content": "a7c0fc212ca26f62f6f13d33b235867b",
            "lastUpdate": "2019-07-10T20:51:11.639Z"
        },
        "0-consul-footer-2019-servicos": {
            "content": "34743c0a16308795eb91d576520edac1",
            "lastUpdate": "2019-07-10T20:51:11.641Z"
        },
        "0-consul-listagem-smartbeer-2": {
            "content": "c2ba744dcf0b42e1217beb13ee80b96f",
            "lastUpdate": "2019-08-26T16:59:51.299Z"
        },
        "0-consul-smartbeer-shelf": {
            "content": "0fc6c8e61238bbf85f24aa2675faa734",
            "lastUpdate": "2019-07-19T20:44:29.779Z"
        },
        "arquivos/consul2-cervejeiras.min.js": {
            "content": "0125e73eff3686b4552d9e4b2a600a8e",
            "lastUpdate": "2019-08-26T16:59:46.953Z"
        },
        "arquivos/consul2-cervejeiras.css": {
            "content": "12cfc61b9af666b29b706538df2b5f0c",
            "lastUpdate": "2019-08-21T15:49:59.269Z"
        },
        "0-consul-prateleira-personalizada": {
            "content": "88b9c8834b35d230ee087bdbb4419d82",
            "lastUpdate": "2019-07-26T20:25:34.354Z"
        },
        "0-consul-produto-kit": {
            "content": "99d8b7e5b05dc3f0cf30871763ca78cd",
            "lastUpdate": "2019-08-26T16:59:51.322Z"
        }
    },
    "consulempresa": {
        "0-consul-footer": {
            "content": "3ec228f02f5ed4e3ce0c438618d32da9",
            "lastUpdate": "2018-10-15T20:44:57.053Z"
        },
        "0-consul-head-content": {
            "content": "b972527176151107b9151c6b0f81c91d",
            "lastUpdate": "2018-10-15T20:44:57.054Z"
        },
        "0-consul-header-landing-aniversario": {
            "content": "0a1034578528692c332dbb04da134a2f",
            "lastUpdate": "2018-07-18T19:19:09.265Z"
        },
        "0-consul-header": {
            "content": "0b2b7ec523678521b9053610e7153fbe",
            "lastUpdate": "2018-10-15T20:44:57.057Z"
        },
        "0-consul-servicos": {
            "content": "cd9055be1a994e6353213406e334dd5d",
            "lastUpdate": "2018-07-18T19:19:09.267Z"
        },
        "0-consul-top-header": {
            "content": "120689e9fbea4c63ed70a0a4eaa5106b",
            "lastUpdate": "2018-07-18T19:19:09.268Z"
        },
        "0-consul-busca-chaordic": {
            "content": "d4cc090f89921b358394cebdf18aa2fa",
            "lastUpdate": "2018-10-15T20:45:08.142Z"
        },
        "0-consul-busca-chaordic2": {
            "content": "5f84de5e78dbdbe8b49278b9f479dd93",
            "lastUpdate": "2018-10-15T20:45:08.144Z"
        },
        "0-consul-busca": {
            "content": "8a79537d0c84df5ec04a549a7a6c6e24",
            "lastUpdate": "2018-10-15T20:45:08.145Z"
        },
        "0-consul-calculadora-btu": {
            "content": "ebfb7b363d9886e437d973cb2ea6da39",
            "lastUpdate": "2018-10-15T20:45:08.147Z"
        },
        "0-consul-home-chaordic": {
            "content": "9d201ba4dc3307acd1e65be832c88e05",
            "lastUpdate": "2018-07-18T19:19:10.766Z"
        },
        "0-consul-home-pj": {
            "content": "ea62d704d541cdbbf4cf3c3ead197784",
            "lastUpdate": "2018-10-15T20:45:08.149Z"
        },
        "0-consul-home": {
            "content": "440e03006fc8a6327336803bf63c79e4",
            "lastUpdate": "2018-10-15T20:45:08.151Z"
        },
        "0-consul-institucional": {
            "content": "1ffa29f797c1755465f7134fab371923",
            "lastUpdate": "2018-10-15T20:45:08.152Z"
        },
        "0-consul-listagem-ar-condicionado": {
            "content": "e5c3e6c873d0e35cbe3504f3e0ee3f7a",
            "lastUpdate": "2018-10-15T20:45:08.153Z"
        },
        "0-consul-listagem": {
            "content": "3ba04a9e92a9678c2bb3491c61febc78",
            "lastUpdate": "2018-10-15T20:45:08.155Z"
        },
        "0-consul-login": {
            "content": "eea7924d9b4f9183ad6cd69f91f7ad24",
            "lastUpdate": "2018-10-15T20:45:08.156Z"
        },
        "0-consul-meuspedidos": {
            "content": "fe65d32a7c527394e41d82095c8e5e59",
            "lastUpdate": "2018-10-15T20:45:08.157Z"
        },
        "0-consul-minhaconta": {
            "content": "045800143cb33fde8c0fab23dcca1ff4",
            "lastUpdate": "2018-10-15T20:45:08.158Z"
        },
        "0-consul-minicart": {
            "content": "9a64cdaf2de672b917e58e378eccc313",
            "lastUpdate": "2018-07-18T19:19:10.776Z"
        },
        "0-consul-neemu": {
            "content": "0f3bcb73e24151b0b3304966097d944a",
            "lastUpdate": "2018-10-15T20:45:08.160Z"
        },
        "0-consul-pedidos": {
            "content": "4c9d95eb7ffe7c08fa5224b74feb031f",
            "lastUpdate": "2018-10-15T20:45:08.161Z"
        },
        "0-consul-produto-quiz": {
            "content": "18adf161d28034871fd2027c82bf0262",
            "lastUpdate": "2018-10-15T20:45:08.162Z"
        },
        "0-consul-produto": {
            "content": "9f631580936b1afc1939fb92c42e9481",
            "lastUpdate": "2018-10-15T20:45:08.164Z"
        },
        "0-consul-destaque": {
            "content": "30aa4f49f3242a72f5524f4af0ddd458",
            "lastUpdate": "2018-07-18T19:19:12.592Z"
        },
        "0-prateleira-default": {
            "content": "ec0a0e7d8fa6eb8538ef46ef91785022",
            "lastUpdate": "2018-07-18T19:19:12.593Z"
        },
        "0-consul-compare": {
            "content": "6d021b2b846ceb1bee32d6c415922a65",
            "lastUpdate": "2018-07-18T19:21:17.554Z"
        },
        "0-consul-landing-birthday-2018-v2": {
            "content": "42733ec2cef780e091bc634c27ef520d",
            "lastUpdate": "2018-07-18T19:21:17.556Z"
        },
        "0-consul-landing-birthday-2018": {
            "content": "2d64fd3d482422e7939759f00b95846a",
            "lastUpdate": "2018-07-18T19:21:17.558Z"
        },
        "0-consul-landing-concurso": {
            "content": "05a04b221e940d01782065fe32897581",
            "lastUpdate": "2018-07-18T19:21:17.559Z"
        },
        "0-consul-landing-de-combos": {
            "content": "652e34b1e88b594719d63c2e205c633a",
            "lastUpdate": "2018-07-18T19:21:17.560Z"
        },
        "0-consul-landing-gae-compra-interno": {
            "content": "3732b35d4d959b759ceb54256b9b327b",
            "lastUpdate": "2018-07-18T19:21:17.561Z"
        },
        "0-consul-landing-gae": {
            "content": "e12bc9d01c72e658ca7ce7fbd6be5d4b",
            "lastUpdate": "2018-07-18T19:21:17.562Z"
        },
        "0-consul-pre-home": {
            "content": "7330092d7be35a40d11dc72984b93b98",
            "lastUpdate": "2018-07-18T19:21:17.565Z"
        },
        "0-consul-produto-calc": {
            "content": "c61f450febd89f80d18b5510fa41045d",
            "lastUpdate": "2018-07-18T19:21:17.566Z"
        },
        "0-consul-smart-beer-QuickView": {
            "content": "0788c12dba79796f8312f4b116b56fb9",
            "lastUpdate": "2018-07-18T19:21:17.568Z"
        },
        "0-consul-smart-beer": {
            "content": "4448f8cdba1938e9558b96475075b7c5",
            "lastUpdate": "2018-07-18T19:21:17.569Z"
        },
        "consul-landing-wonderland": {
            "content": "2b813af081147fc029095c69701307c9",
            "lastUpdate": "2018-07-18T19:21:17.570Z"
        },
        "files/checkout-confirmation-custom.js": {
            "content": "e51a2c7577d669841a17a6ed1090a9c1",
            "lastUpdate": "2019-04-24T13:39:07.140Z"
        },
        "files/checkout5-custom.js": {
            "content": "7076b5ea40fcc99a982bdd60a407e2ae",
            "lastUpdate": "2019-04-24T13:39:07.143Z"
        },
        "arquivos/checkout-confirmation-custom.min.js": {
            "content": "f9a4b1a45320d81037937b8f397e3fec",
            "lastUpdate": "2018-10-15T20:44:53.721Z"
        },
        "arquivos/checkout5-custom.css": {
            "content": "129e0e94cf18f3ac27a97a5e07c49c6c",
            "lastUpdate": "2018-10-15T20:44:53.722Z"
        },
        "arquivos/checkout5-custom.min.js": {
            "content": "2e91af8e7c6b8e65b51fab9d48560f32",
            "lastUpdate": "2018-10-15T20:44:53.723Z"
        },
        "arquivos/consul2-account.css": {
            "content": "124941905f12684457d920408649c49d",
            "lastUpdate": "2018-08-03T19:44:25.001Z"
        },
        "arquivos/consul2-app.min.js": {
            "content": "67d36130884cb46eb74c22b208df9d5f",
            "lastUpdate": "2018-10-15T20:44:53.725Z"
        },
        "arquivos/consul2-bf.css": {
            "content": "6df7562e0480da660ce09282abeb4c5b",
            "lastUpdate": "2018-08-03T19:44:25.004Z"
        },
        "arquivos/consul2-home.css": {
            "content": "b4d5da1dcc68f1f2ac66b32c0048ec1d",
            "lastUpdate": "2018-10-15T20:44:53.728Z"
        },
        "arquivos/consul2-home.min.js": {
            "content": "444fc1bdcfe106b9bc059973e0e5e938",
            "lastUpdate": "2018-10-15T20:44:53.729Z"
        },
        "arquivos/consul2-institucional.css": {
            "content": "5da034d6434153ff537dbd25b93dd96c",
            "lastUpdate": "2018-08-03T19:44:25.009Z"
        },
        "arquivos/consul2-listagem.css": {
            "content": "e2fff2355ebc51b59415a5c08cd1086a",
            "lastUpdate": "2018-10-15T20:44:53.730Z"
        },
        "arquivos/consul2-listagem.min.js": {
            "content": "85369b289aee6dab0b297a8c6891d49f",
            "lastUpdate": "2018-10-15T20:44:53.731Z"
        },
        "arquivos/consul2-login.css": {
            "content": "575474ca35edf17a25d2cb5e16d4cecd",
            "lastUpdate": "2018-08-03T19:44:25.012Z"
        },
        "arquivos/consul2-myorders.css": {
            "content": "297c7ead7c151905fcace945d1a6f987",
            "lastUpdate": "2018-08-15T14:53:07.780Z"
        },
        "arquivos/consul2-myorders.min.js": {
            "content": "0ce4d9ac9a383ad656131c1449da3969",
            "lastUpdate": "2018-10-15T20:44:53.733Z"
        },
        "arquivos/consul2-produto.css": {
            "content": "c378a42c8f928226c4887dec4bff4d3c",
            "lastUpdate": "2018-10-15T20:44:53.734Z"
        },
        "arquivos/consul2-produto.min.js": {
            "content": "d265dd3cad0517a73b134e5846cea49d",
            "lastUpdate": "2018-10-15T20:44:53.736Z"
        },
        "arquivos/consul2-style.css": {
            "content": "ea0215e82ae44bb871a63c8672a91879",
            "lastUpdate": "2018-08-15T14:53:07.785Z"
        },
        "arquivos/consulcoheadline_std_bd-webfont.eot.css": {
            "content": "9f841292bb0ce05058ce1f8044bc7fb7",
            "lastUpdate": "2018-08-03T19:44:25.019Z"
        },
        "arquivos/consulcoheadline_std_bd-webfont.svg.css": {
            "content": "7c1edfcd005b803656a6ce5771639655",
            "lastUpdate": "2018-08-03T19:44:25.020Z"
        },
        "arquivos/consulcoheadline_std_bd-webfont.ttf.css": {
            "content": "1575c74d280e049f899c6ad3112f619d",
            "lastUpdate": "2018-08-03T19:44:25.021Z"
        },
        "arquivos/consulcoheadline_std_bd-webfont.woff.css": {
            "content": "e633e875f417c82fd60e0c61d8338ca4",
            "lastUpdate": "2018-08-03T19:44:25.022Z"
        },
        "arquivos/consulcoheadline_std_bd-webfont.woff2.css": {
            "content": "630b55510c5038c047d150a83e799760",
            "lastUpdate": "2018-08-03T19:44:25.023Z"
        },
        "arquivos/consulcoheadline_std_lt-webfont.eot.css": {
            "content": "1c4fe2c1d17e0657ba62e29703fe9056",
            "lastUpdate": "2018-08-03T19:44:25.025Z"
        },
        "arquivos/consulcoheadline_std_lt-webfont.svg.css": {
            "content": "9310afe71921eccdec8f1c2295a40d6a",
            "lastUpdate": "2018-08-03T19:44:25.026Z"
        },
        "arquivos/consulcoheadline_std_lt-webfont.ttf.css": {
            "content": "fa1b65231bb9eff77aff64a8a32dc867",
            "lastUpdate": "2018-08-03T19:44:25.027Z"
        },
        "arquivos/consulcoheadline_std_lt-webfont.woff.css": {
            "content": "eb20324d1dcf18829a69d7aa449f9ca0",
            "lastUpdate": "2018-08-03T19:44:25.028Z"
        },
        "arquivos/consulcoheadline_std_lt-webfont.woff2.css": {
            "content": "88c4f9c8aba9f4cae24b1b85626ff450",
            "lastUpdate": "2018-08-03T19:44:25.029Z"
        },
        "arquivos/consulcoheadline_std_rg-webfont.eot.css": {
            "content": "adbd11acf6b41c9f1d6ddd0aef2fea56",
            "lastUpdate": "2018-08-03T19:44:25.030Z"
        },
        "arquivos/consulcoheadline_std_rg-webfont.svg.css": {
            "content": "929f9f03b1b8023348e5990709d61a25",
            "lastUpdate": "2018-08-03T19:44:25.031Z"
        },
        "arquivos/consulcoheadline_std_rg-webfont.ttf.css": {
            "content": "d7e907694a37503f98b3061f0e2ce2fe",
            "lastUpdate": "2018-08-03T19:44:25.033Z"
        },
        "arquivos/consulcoheadline_std_rg-webfont.woff.css": {
            "content": "25e77d5683da517163cf0ccfa87d990f",
            "lastUpdate": "2018-08-03T19:44:25.034Z"
        },
        "arquivos/consulcoheadline_std_rg-webfont.woff2.css": {
            "content": "5d8beba595a3f9b27aecf9baf8129ac4",
            "lastUpdate": "2018-08-03T19:44:25.036Z"
        },
        "arquivos/whirlpool2.eot.css": {
            "content": "1d0d27842af8d0d9cabd631dba2419a2",
            "lastUpdate": "2018-08-03T19:44:25.038Z"
        },
        "arquivos/whirlpool2.svg.css": {
            "content": "f338b6a98422f3bca293f6aa1e6a3da5",
            "lastUpdate": "2018-08-03T19:44:25.039Z"
        },
        "arquivos/whirlpool2.ttf.css": {
            "content": "0e886f7587174060aa7296dd2a4438bb",
            "lastUpdate": "2018-08-03T19:44:25.041Z"
        },
        "arquivos/whirlpool2.woff.css": {
            "content": "f89cea8facdce5557e6b6831d2cc0450",
            "lastUpdate": "2018-08-03T19:44:25.042Z"
        },
        "arquivos/whirlpool2.woff2.css": {
            "content": "e6cabbbdbbc4e2b231e3f7af8c88601b",
            "lastUpdate": "2018-08-03T19:44:25.044Z"
        },
        "files/checkout5-custom.css": {
            "content": "ad96de887f742f0942504fb93b0a756b",
            "lastUpdate": "2019-04-24T13:39:07.142Z"
        },
        "arquivos/consul2-cta.min.js": {
            "content": "1be630e5dbcabb258ea5e20d5668aa2f",
            "lastUpdate": "2018-10-15T20:44:53.726Z"
        },
        "0-consul-cta": {
            "content": "5caa9ca5b5b5f2bf7a92b4e3fb719be3",
            "lastUpdate": "2018-10-15T20:45:08.148Z"
        }
    },
    "consulqa": {
        "files/checkout5-custom.css": {
            "content": "f116e34a1a3def9afe1578faedc8c70c",
            "lastUpdate": "2019-08-26T21:11:18.473Z"
        },
        "files/consul2-account.css": {
            "content": "a98f9c1c55f24e35e38af151988005c0",
            "lastUpdate": "2019-08-26T14:27:08.834Z"
        },
        "files/consul2-bf-2018.css": {
            "content": "d6cf553878690ca4bb9e2916b1dd782a",
            "lastUpdate": "2019-08-26T14:27:08.838Z"
        },
        "files/consul2-bf.css": {
            "content": "136530a7d1157a0604018e63f908a492",
            "lastUpdate": "2019-06-03T19:34:56.128Z"
        },
        "files/consul2-coupon.css": {
            "content": "5681d7bc8c2b894d1fbb5e76fcf8a8d7",
            "lastUpdate": "2019-06-03T19:34:56.130Z"
        },
        "files/consul2-fonts.css": {
            "content": "30af80459c5d644a3c0be84fef72246c",
            "lastUpdate": "2019-06-03T19:34:56.132Z"
        },
        "files/consul2-home.css": {
            "content": "6a6847336c4d5fa17f83b9a918391fcf",
            "lastUpdate": "2019-08-26T21:11:18.529Z"
        },
        "files/consul2-icons.css": {
            "content": "e0d82e70c1b5bb9d2846201dd2529a99",
            "lastUpdate": "2019-06-03T19:34:56.138Z"
        },
        "files/consul2-institucional.css": {
            "content": "34886ff087a451e1ee1e270704207ad0",
            "lastUpdate": "2019-08-26T21:11:18.536Z"
        },
        "files/consul2-listagem.css": {
            "content": "02649b7c5305502dfdc84bc56546ea68",
            "lastUpdate": "2019-08-26T21:11:18.539Z"
        },
        "files/consul2-login.css": {
            "content": "80b1c1334065b03214ad825a43af1837",
            "lastUpdate": "2019-08-26T21:11:18.545Z"
        },
        "files/consul2-myorders.css": {
            "content": "0b4b7dc06253b1af6dc2cb80c58ef43c",
            "lastUpdate": "2019-08-26T14:27:08.869Z"
        },
        "files/consul2-produto.css": {
            "content": "04719586f53c859a4e2f23d54389d999",
            "lastUpdate": "2019-08-26T21:11:18.554Z"
        },
        "files/consul2-style.css": {
            "content": "46edd009fa2253d0b6a89ec7ad8ae805",
            "lastUpdate": "2019-08-26T21:11:18.558Z"
        },
        "arquivos/consulcoheadline_std_bd-webfont.eot.css": {
            "content": "13b2a15696384e6546d1ebc17469be29",
            "lastUpdate": "2019-08-19T16:21:21.835Z"
        },
        "arquivos/consulcoheadline_std_bd-webfont.svg.css": {
            "content": "7c1edfcd005b803656a6ce5771639655",
            "lastUpdate": "2019-08-20T17:38:02.616Z"
        },
        "arquivos/consulcoheadline_std_bd-webfont.ttf.css": {
            "content": "5d20b3bf4856b474497772b93ca5edd4",
            "lastUpdate": "2019-08-19T16:21:21.839Z"
        },
        "arquivos/consulcoheadline_std_bd-webfont.woff.css": {
            "content": "a24fb1d6623e1a879bd6ce2410f8620c",
            "lastUpdate": "2019-08-19T16:21:21.842Z"
        },
        "arquivos/consulcoheadline_std_bd-webfont.woff2.css": {
            "content": "ebd6a9b6e9f949cea33b3765464afcc1",
            "lastUpdate": "2019-08-19T16:21:21.844Z"
        },
        "arquivos/consulcoheadline_std_lt-webfont.eot.css": {
            "content": "1d3accb3c60bf790aa55c45635d7ff5b",
            "lastUpdate": "2019-08-19T16:21:21.846Z"
        },
        "arquivos/consulcoheadline_std_lt-webfont.svg.css": {
            "content": "9310afe71921eccdec8f1c2295a40d6a",
            "lastUpdate": "2019-08-20T17:38:02.633Z"
        },
        "arquivos/consulcoheadline_std_lt-webfont.ttf.css": {
            "content": "0b5ea22ef1f79c158550b50e688ba445",
            "lastUpdate": "2019-08-19T16:21:21.849Z"
        },
        "arquivos/consulcoheadline_std_lt-webfont.woff.css": {
            "content": "bef9063956e6c10b072ee6d8c97281b6",
            "lastUpdate": "2019-08-19T16:21:21.851Z"
        },
        "arquivos/consulcoheadline_std_lt-webfont.woff2.css": {
            "content": "9917e5cbf336138d8aa0bfe3f364be5e",
            "lastUpdate": "2019-08-19T16:21:21.852Z"
        },
        "arquivos/consulcoheadline_std_rg-webfont.eot.css": {
            "content": "94a294365dcb7cbe4e1c54b39e384091",
            "lastUpdate": "2019-08-19T16:21:21.854Z"
        },
        "arquivos/consulcoheadline_std_rg-webfont.svg.css": {
            "content": "929f9f03b1b8023348e5990709d61a25",
            "lastUpdate": "2019-08-20T17:38:02.648Z"
        },
        "arquivos/consulcoheadline_std_rg-webfont.ttf.css": {
            "content": "b630c09e3ee56c6a0d05fa6bc4889b02",
            "lastUpdate": "2019-08-19T16:21:21.859Z"
        },
        "arquivos/consulcoheadline_std_rg-webfont.woff.css": {
            "content": "9bb77b94b823cbe8fbe3b7899d297e28",
            "lastUpdate": "2019-08-19T16:21:21.862Z"
        },
        "arquivos/consulcoheadline_std_rg-webfont.woff2.css": {
            "content": "179f798eb0d872074c48067d047f3dd5",
            "lastUpdate": "2019-08-19T16:21:21.864Z"
        },
        "arquivos/whirlpool2.eot.css": {
            "content": "af1e9544d9a341d4b882d3e6b9534fdc",
            "lastUpdate": "2019-08-19T16:21:21.867Z"
        },
        "arquivos/whirlpool2.svg.css": {
            "content": "f338b6a98422f3bca293f6aa1e6a3da5",
            "lastUpdate": "2019-08-20T17:38:02.665Z"
        },
        "arquivos/whirlpool2.ttf.css": {
            "content": "e7639a56979c74776fa35cd1bdc03968",
            "lastUpdate": "2019-08-19T16:21:21.875Z"
        },
        "arquivos/whirlpool2.woff.css": {
            "content": "3af078c9908279729c57b8ccf0fcb140",
            "lastUpdate": "2019-08-19T16:21:21.878Z"
        },
        "arquivos/whirlpool2.woff2.css": {
            "content": "e122b1e5d3abd6c496bdac0129e700df",
            "lastUpdate": "2019-08-19T16:21:21.880Z"
        },
        "0-consul-footer-2019": {
            "content": "82d402b6315eb6f69e0c767e346896aa",
            "lastUpdate": "2019-06-04T10:22:41.307Z"
        },
        "0-consul-footer": {
            "content": "d3c5c753469836ab392b8f4536466d40",
            "lastUpdate": "2019-08-26T21:11:20.726Z"
        },
        "0-consul-head-content": {
            "content": "aa5856153bd40044c75f7d164b50c04f",
            "lastUpdate": "2019-08-26T21:11:20.730Z"
        },
        "0-consul-header-landing-aniversario": {
            "content": "0a1034578528692c332dbb04da134a2f",
            "lastUpdate": "2019-08-20T17:38:04.196Z"
        },
        "0-consul-header": {
            "content": "1ca62a653c3475d1e6277dbb6ee8e44d",
            "lastUpdate": "2019-07-25T15:26:44.392Z"
        },
        "0-consul-servicos": {
            "content": "cd9055be1a994e6353213406e334dd5d",
            "lastUpdate": "2019-08-20T17:38:04.202Z"
        },
        "0-consul-top-header": {
            "content": "37b64caf4e4fe78ca7fb93cd7b6a7b75",
            "lastUpdate": "2019-08-07T19:53:30.517Z"
        },
        "0-consul-busca-chaordic": {
            "content": "b4e13984864512db2c576dfbb41ec00e",
            "lastUpdate": "2019-08-26T21:11:23.725Z"
        },
        "0-consul-busca-chaordic2": {
            "content": "aa67a2f3494b6fdbc3907925360eb728",
            "lastUpdate": "2019-08-26T21:11:23.730Z"
        },
        "0-consul-busca": {
            "content": "923eddfa3bb2a091b782ebf987b6c043",
            "lastUpdate": "2019-08-26T21:11:23.736Z"
        },
        "0-consul-calculadora-btu": {
            "content": "6ea15bf8e91a7b8098bfb8c78270dd0c",
            "lastUpdate": "2019-08-26T21:11:23.740Z"
        },
        "0-consul-cta": {
            "content": "eebb0fa09c0ba72c597c3f3fc2836541",
            "lastUpdate": "2019-08-26T21:11:23.755Z"
        },
        "0-consul-home-chaordic": {
            "content": "290133e6cb99daeddbb0a15f0645984e",
            "lastUpdate": "2019-07-11T19:15:19.354Z"
        },
        "0-consul-home-pj": {
            "content": "abd7b26de07e28dab625ccf10d220ec3",
            "lastUpdate": "2019-08-26T21:11:23.762Z"
        },
        "0-consul-home": {
            "content": "f9e6a3e9d6625bfa1d5dbacd5d82f2d1",
            "lastUpdate": "2019-08-26T21:11:23.764Z"
        },
        "0-consul-institucional": {
            "content": "8cb8b9bda36e23de4c34580bd1b5dbc9",
            "lastUpdate": "2019-08-26T21:11:23.769Z"
        },
        "0-consul-listagem-ar-condicionado": {
            "content": "bae04607231ea78dede1817ba31228e2",
            "lastUpdate": "2019-08-26T21:11:23.796Z"
        },
        "0-consul-listagem": {
            "content": "b820f5e640e57183869e05801ea434ea",
            "lastUpdate": "2019-08-26T21:11:23.802Z"
        },
        "0-consul-login": {
            "content": "f4f166dda03406761c3353d85188a30e",
            "lastUpdate": "2019-08-26T21:11:23.805Z"
        },
        "0-consul-meuspedidos": {
            "content": "6782ab9a5e291e37f24c17e517ba9c65",
            "lastUpdate": "2019-08-26T21:11:23.807Z"
        },
        "0-consul-minhaconta": {
            "content": "08a5889e8d06265c6e2e463de2cdc573",
            "lastUpdate": "2019-08-26T21:11:23.810Z"
        },
        "0-consul-minicart": {
            "content": "9a64cdaf2de672b917e58e378eccc313",
            "lastUpdate": "2019-08-20T17:38:07.161Z"
        },
        "0-consul-neemu": {
            "content": "335df5ca7e88ed80aeba246206f6196d",
            "lastUpdate": "2019-08-26T21:11:23.812Z"
        },
        "0-consul-pedidos": {
            "content": "69e765d4a8d763b1c42d5b8eb156ecef",
            "lastUpdate": "2019-08-26T21:11:23.815Z"
        },
        "0-consul-produto-quiz": {
            "content": "d36939f2c9e10f2719cd4c1f4695030d",
            "lastUpdate": "2019-08-26T21:11:23.824Z"
        },
        "0-consul-produto-refri": {
            "content": "dcbdbdf22f77b66c632e0214ad9537e9",
            "lastUpdate": "2019-08-26T21:11:23.826Z"
        },
        "0-consul-produto": {
            "content": "86a826c0e499cba48f086f1d956c7019",
            "lastUpdate": "2019-08-26T21:11:23.829Z"
        },
        "0-consul-destaque": {
            "content": "d7f915c8e65e231b6c1bb3bc35dc37e5",
            "lastUpdate": "2019-07-05T18:59:41.734Z"
        },
        "0-consul-prateleira-default": {
            "content": "f81a7091d94eacdc721f9e397d2eeea8",
            "lastUpdate": "2019-07-26T14:12:26.218Z"
        },
        "0-prateleira-default": {
            "content": "fe2d177dbc38f32bf13d7ff2fb0ecc38",
            "lastUpdate": "2019-07-05T18:59:41.739Z"
        },
        "0-shelf-blackfriday-2018": {
            "content": "27658782b45d01f5cdd77121871f9332",
            "lastUpdate": "2019-08-20T17:38:09.419Z"
        },
        "0-consul-footer-2019-after": {
            "content": "cb34995d945d152bda1ed306f6873280",
            "lastUpdate": "2019-08-26T21:11:20.715Z"
        },
        "0-consul-footer-2019-atendimento": {
            "content": "1879b4ce64390f78b83312d99efa7c6f",
            "lastUpdate": "2019-07-11T19:15:16.443Z"
        },
        "0-consul-footer-2019-bottom": {
            "content": "5da9045db5f95954d1142b8345c152be",
            "lastUpdate": "2019-08-20T17:38:04.164Z"
        },
        "0-consul-footer-2019-menu": {
            "content": "bfd94f8e0ae4b88b3d302d52c282919a",
            "lastUpdate": "2019-07-11T19:15:16.448Z"
        },
        "0-consul-footer-2019-newsletter": {
            "content": "a7c0fc212ca26f62f6f13d33b235867b",
            "lastUpdate": "2019-07-11T19:15:16.455Z"
        },
        "0-consul-footer-2019-servicos": {
            "content": "34743c0a16308795eb91d576520edac1",
            "lastUpdate": "2019-07-11T19:15:16.457Z"
        },
        "files/checkout-confirmation-custom.js": {
            "content": "7ebe23a5f739e1cb5ff5b46c7cab3c03",
            "lastUpdate": "2019-08-26T21:11:18.466Z"
        },
        "files/checkout-confirmation-custom.min.js": {
            "content": "7ebe23a5f739e1cb5ff5b46c7cab3c03",
            "lastUpdate": "2019-08-26T21:11:18.471Z"
        },
        "files/checkout5-custom.js": {
            "content": "bf765f405fede4636660e60d64b490f8",
            "lastUpdate": "2019-08-26T21:11:18.476Z"
        },
        "files/checkout5-custom.min.js": {
            "content": "bf765f405fede4636660e60d64b490f8",
            "lastUpdate": "2019-08-26T21:11:18.478Z"
        },
        "files/consul2-app.min.js": {
            "content": "316f6ce25b453542b6fbeee899c48f2f",
            "lastUpdate": "2019-08-26T21:11:18.514Z"
        },
        "files/consul2-cta.min.js": {
            "content": "20d43330e11af78e8f12561ff94bb0a4",
            "lastUpdate": "2019-08-26T21:11:18.525Z"
        },
        "files/consul2-home.min.js": {
            "content": "71740365e014fdc4b2757650ef9bf534",
            "lastUpdate": "2019-08-26T21:11:18.532Z"
        },
        "files/consul2-listagem.min.js": {
            "content": "5a0ca2d7ad505ae78fe681ec9a674480",
            "lastUpdate": "2019-08-26T21:11:18.542Z"
        },
        "files/consul2-myorders.min.js": {
            "content": "c75b1c268463b49c2feae0733b26ce71",
            "lastUpdate": "2019-08-26T21:11:18.548Z"
        },
        "files/consul2-produto.min.js": {
            "content": "a8c2baea899ae7df0239f69aff66219c",
            "lastUpdate": "2019-08-26T21:11:18.556Z"
        },
        "0-consul-listagem-smartbeer-2": {
            "content": "243a5db68d5d12b42dea4caadd5dafd1",
            "lastUpdate": "2019-08-26T21:11:23.799Z"
        },
        "0-consul-smartbeer-shelf": {
            "content": "0fc6c8e61238bbf85f24aa2675faa734",
            "lastUpdate": "2019-07-18T21:18:21.856Z"
        },
        "files/consul2-cervejeiras.min.js": {
            "content": "4582eccad9e472065f87775bd7e287d7",
            "lastUpdate": "2019-08-26T21:11:18.518Z"
        },
        "files/consul2-cervejeiras.css": {
            "content": "b66e591304490bf4267a1a168f1f6ebc",
            "lastUpdate": "2019-08-26T14:27:08.841Z"
        },
        "0-consul-prateleira-personalizada": {
            "content": "a9581fac3130402ecf51235492414782",
            "lastUpdate": "2019-07-26T14:12:26.222Z"
        },
        "0-consul-produto-kit": {
            "content": "d506d411dd14c322460499840657e171",
            "lastUpdate": "2019-08-26T21:11:23.822Z"
        },
        "files/calculadora-btu.min.js": {
            "content": "16b82586ff9650300342cc74c943eca5",
            "lastUpdate": "2019-08-26T21:11:18.460Z"
        },
        "files/cns-coupon.css": {
            "content": "4d2da9aa4ab13adedf310feda41a0ade",
            "lastUpdate": "2019-08-26T21:11:18.481Z"
        },
        "files/cns-coupon.min.js": {
            "content": "2fe4bf315c7691587af22ebd1701ffe7",
            "lastUpdate": "2019-08-26T21:11:18.484Z"
        },
        "files/cns-performance-page-blackfriday-2018.min.js": {
            "content": "42385a571b6c3b82996ea9c01dc214d9",
            "lastUpdate": "2019-08-26T21:11:18.486Z"
        },
        "files/consul-cupom.min.js": {
            "content": "8c0112ed0e5469c517e97851bb521674",
            "lastUpdate": "2019-08-26T21:11:18.489Z"
        },
        "files/consul-dia-das-maes.min.js": {
            "content": "cc076e481a0e6c948851b8c9df39adc0",
            "lastUpdate": "2019-08-26T21:11:18.492Z"
        },
        "files/consul-landing-blackfriday-2018.css": {
            "content": "bc8fbbc8efc9c63dd13996414095e505",
            "lastUpdate": "2019-08-26T14:27:08.818Z"
        },
        "files/consul-landing-blackfriday-2018.min.js": {
            "content": "a17571bbf581ce3719172e31329ef409",
            "lastUpdate": "2019-08-26T21:11:18.495Z"
        },
        "files/consul-landing-combos.min.js": {
            "content": "7a8d7d6ace6a90433b84dc354603c785",
            "lastUpdate": "2019-08-26T21:11:18.498Z"
        },
        "files/consul-landing-concurso.min.js": {
            "content": "19c15b57de09eb19575f5ae3d521032d",
            "lastUpdate": "2019-08-26T21:11:18.502Z"
        },
        "files/consul-landing-gae-2017.min.js": {
            "content": "cb8d153bcfa5cd548c9a9cc6fbb0c017",
            "lastUpdate": "2019-08-26T21:11:18.505Z"
        },
        "files/consul-landing-wonderland.min.js": {
            "content": "122309d065a0bce9a8b57a72598161fe",
            "lastUpdate": "2019-08-26T21:11:18.508Z"
        },
        "files/consul-rastreio.min.js": {
            "content": "ea182c451e8931404ca9847a2d4d74ef",
            "lastUpdate": "2019-08-26T21:11:18.511Z"
        },
        "files/consul2-comparador.css": {
            "content": "58e9767423a002bf16b07a5b162267fa",
            "lastUpdate": "2019-08-26T21:11:18.521Z"
        },
        "files/consul2-comparador.min.js": {
            "content": "58276acd8b4a36376a33a1249ab579bc",
            "lastUpdate": "2019-08-26T21:11:18.523Z"
        },
        "files/consul2-pre-home.min.js": {
            "content": "76c4a228b3d28801ffbb24b63a58422a",
            "lastUpdate": "2019-08-26T21:11:18.551Z"
        },
        "files/cozinha-ambientada.css": {
            "content": "aaf65fa101eca6d45ca025e3297258ad",
            "lastUpdate": "2019-08-26T21:11:18.560Z"
        },
        "files/cozinha-ambientada.min.js": {
            "content": "5c4a3fede119a62dc8079d7f0aacad32",
            "lastUpdate": "2019-08-26T21:11:18.562Z"
        },
        "files/cupom-novo.css": {
            "content": "80080b4198d17339a478f5b2aec9dc7d",
            "lastUpdate": "2019-08-26T21:11:18.565Z"
        },
        "files/custom-datalayer.min.js": {
            "content": "dee6ecb161aefcfb9c2f711d3ed69698",
            "lastUpdate": "2019-08-26T21:11:18.568Z"
        },
        "files/footer-2019.css": {
            "content": "d53ab249d2ce59d2616757bcf5acaa19",
            "lastUpdate": "2019-08-26T14:30:24.807Z"
        },
        "files/footer-2019.min.js": {
            "content": "e5bf5d025f60a915215cfe954f4d2b63",
            "lastUpdate": "2019-08-26T14:30:24.809Z"
        },
        "files/landing-birthday-2018-2.css": {
            "content": "0c48f29249c2257a7d0d8fce78ad1558",
            "lastUpdate": "2019-08-26T14:27:08.898Z"
        },
        "files/landing-birthday-2018-2.min.js": {
            "content": "250376157b77c172e40fa09b7909c378",
            "lastUpdate": "2019-08-26T21:11:18.570Z"
        },
        "files/landing-birthday-2018.css": {
            "content": "fa214097bb02921f4eb0ee3f5a8e5896",
            "lastUpdate": "2019-08-26T14:27:08.903Z"
        },
        "files/landing-birthday-2018.min.js": {
            "content": "aa756740b6daad4ddd6550708796e7ce",
            "lastUpdate": "2019-08-26T21:11:18.573Z"
        },
        "files/landing-gae-2019.min.js": {
            "content": "01d8f0f3f4af19ca5726d829dd534ff4",
            "lastUpdate": "2019-08-26T21:11:18.576Z"
        },
        "files/landing-gae-compra-interno.min.js": {
            "content": "f9b1eb80f6a51efe961cd1db4e1d2aa6",
            "lastUpdate": "2019-08-26T21:11:18.578Z"
        },
        "files/simulador-lavadora.min.js": {
            "content": "05c2ffee506d36afc2254ae839603944",
            "lastUpdate": "2019-08-26T21:11:18.581Z"
        },
        "files/smart-beer-custom.min.js": {
            "content": "8f0c1cedf3adb63e5c5817034c20741b",
            "lastUpdate": "2019-08-26T21:11:18.584Z"
        },
        "files/smart-beer.min.js": {
            "content": "d36ef2cb609c49cb771afb16960b23b4",
            "lastUpdate": "2019-08-26T21:11:18.586Z"
        },
        "0-consul-compare": {
            "content": "46e65bc9b5e8e540aff5877c02147039",
            "lastUpdate": "2019-08-26T21:11:23.744Z"
        },
        "0-consul-coupon": {
            "content": "71f41ded43a7a529b2f40a1ff963cc67",
            "lastUpdate": "2019-08-26T21:11:23.752Z"
        },
        "0-consul-cozinha-ambientada": {
            "content": "9645e98dd2c9190b41c2651e751c5300",
            "lastUpdate": "2019-08-26T14:44:46.022Z"
        },
        "0-consul-cupom": {
            "content": "1d44344314d1c38f32a7164bb285c15f",
            "lastUpdate": "2019-08-26T21:11:23.758Z"
        },
        "0-consul-landing-birthday-2018-v2": {
            "content": "acda882faba4fd71f80b318a570f848f",
            "lastUpdate": "2019-08-26T21:11:23.772Z"
        },
        "0-consul-landing-birthday-2018": {
            "content": "e5b4e4b45c08665ca8812b9be50c45e7",
            "lastUpdate": "2019-08-26T21:11:23.775Z"
        },
        "0-consul-landing-blackfriday-2018": {
            "content": "221c76b4e128eeb99255489c7b7789fe",
            "lastUpdate": "2019-08-26T14:44:46.045Z"
        },
        "0-consul-landing-concurso": {
            "content": "b64f9ed9fad269534da9a6b3ae892642",
            "lastUpdate": "2019-08-26T21:11:23.778Z"
        },
        "0-consul-landing-de-combos": {
            "content": "fe88e38cf0c946bda1431ed17ed4490d",
            "lastUpdate": "2019-08-26T21:11:23.782Z"
        },
        "0-consul-landing-dia-das-maes": {
            "content": "a122b4d81fd7d2df0e0064b2da1ce9c2",
            "lastUpdate": "2019-08-26T21:11:23.785Z"
        },
        "0-consul-landing-gae-2019": {
            "content": "66ed04579fd4e45c24de98e11297a98d",
            "lastUpdate": "2019-08-26T21:11:23.788Z"
        },
        "0-consul-landing-gae-compra-interno": {
            "content": "f0901c0a34b7db7c24a90440aa8bc8ca",
            "lastUpdate": "2019-08-26T21:11:23.790Z"
        },
        "0-consul-landing-gae": {
            "content": "f6db21d3075e0631f705ac48f3e0180e",
            "lastUpdate": "2019-08-26T21:11:23.793Z"
        },
        "0-consul-pre-home": {
            "content": "eb497ee3a0b3cb59af48051c18b81e88",
            "lastUpdate": "2019-08-26T21:11:23.817Z"
        },
        "0-consul-produto-calc": {
            "content": "732b8e942f1491145f1cef6ec4da4411",
            "lastUpdate": "2019-08-26T21:11:23.820Z"
        },
        "0-consul-smart-beer-QuickView": {
            "content": "9a02803531fa98c802642f6a15ad675d",
            "lastUpdate": "2019-08-26T21:11:23.833Z"
        },
        "0-consul-smart-beer": {
            "content": "79d23676d8ec0eedf513c022632cbbad",
            "lastUpdate": "2019-08-26T21:11:23.836Z"
        },
        "0-performance-page-blackfriday-2018": {
            "content": "e249666b7797585c1a534a6582e5fb99",
            "lastUpdate": "2019-08-26T14:44:46.105Z"
        },
        "0-Rastreio": {
            "content": "20bb94f684fa3bc5b1b5f05db55fea25",
            "lastUpdate": "2019-08-26T14:44:46.108Z"
        },
        "consul-landing-wonderland": {
            "content": "3f1b8dca408f7f545b7dde5939d3ede8",
            "lastUpdate": "2019-08-26T21:11:23.839Z"
        }
    }
}
