{
    "consul": {
        "files/checkout5-custom.css": {
            "content": "a1cb2463bf69f41da144cd49a22b2d53",
            "lastUpdate": "2020-06-17T19:08:35.643Z"
        },
        "arquivos/checkout5-custom.css": {
            "content": "a1cb2463bf69f41da144cd49a22b2d53",
            "lastUpdate": "2020-06-17T19:08:39.578Z"
        },
        "arquivos/consul-icons.svg.css": {
            "content": "d41d8cd98f00b204e9800998ecf8427e",
            "lastUpdate": "2020-06-15T20:07:53.019Z"
        },
        "arquivos/consul2-account.css": {
            "content": "a98f9c1c55f24e35e38af151988005c0",
            "lastUpdate": "2020-06-17T19:08:39.579Z"
        },
        "arquivos/consul2-bf-2018.css": {
            "content": "d6cf553878690ca4bb9e2916b1dd782a",
            "lastUpdate": "2020-06-15T20:07:53.087Z"
        },
        "arquivos/consul2-bf.css": {
            "content": "136530a7d1157a0604018e63f908a492",
            "lastUpdate": "2020-06-17T19:08:39.580Z"
        },
        "arquivos/consul2-cervejeiras.css": {
            "content": "ccf06ae2cc259c1be1fcfcd981f3441f",
            "lastUpdate": "2020-06-17T19:08:39.581Z"
        },
        "arquivos/consul2-coupon.css": {
            "content": "5681d7bc8c2b894d1fbb5e76fcf8a8d7",
            "lastUpdate": "2020-06-15T20:07:53.125Z"
        },
        "arquivos/consul2-fonts.css": {
            "content": "30af80459c5d644a3c0be84fef72246c",
            "lastUpdate": "2020-06-15T20:07:53.125Z"
        },
        "arquivos/consul2-footer-bf2019.css": {
            "content": "1031eff50c0ab6b1157c5e9c435c8ef7",
            "lastUpdate": "2020-06-15T20:07:53.126Z"
        },
        "arquivos/consul2-header-bf2019.css": {
            "content": "2ee6d3c3b21ca943107a82baaf0d5d96",
            "lastUpdate": "2020-06-15T20:07:53.126Z"
        },
        "arquivos/consul2-home-bf2019.css": {
            "content": "504c8dfbeba9ea91d26bc431e27bd4cd",
            "lastUpdate": "2020-06-17T19:08:39.583Z"
        },
        "arquivos/consul2-home-cw2020.css": {
            "content": "bb8f5cc2adae2102bd430e3ac2ba341a",
            "lastUpdate": "2020-06-17T19:08:39.583Z"
        },
        "arquivos/consul2-home.css": {
            "content": "9e3c4c17abbfcf6d5c94aa4cc4dbd336",
            "lastUpdate": "2020-06-17T19:08:39.584Z"
        },
        "arquivos/consul2-icons.css": {
            "content": "ae93c4b15b3cde21bddf23f782563c3a",
            "lastUpdate": "2020-06-15T20:07:53.128Z"
        },
        "arquivos/consul2-institucional.css": {
            "content": "2c6e05c89d37d2f64289d1f8e04e35d6",
            "lastUpdate": "2020-06-17T19:08:39.585Z"
        },
        "arquivos/consul2-linha-embutir.css": {
            "content": "63c2644923d06827d85a8dc040827197",
            "lastUpdate": "2020-06-17T19:08:39.586Z"
        },
        "arquivos/consul2-listagem-embutidos.css": {
            "content": "ea877d84501af6c00a63cb1301cabe23",
            "lastUpdate": "2020-06-17T19:08:39.587Z"
        },
        "arquivos/consul2-listagem.css": {
            "content": "c881dcd209d4eca49d33a2814a95687a",
            "lastUpdate": "2020-06-17T19:08:39.588Z"
        },
        "arquivos/consul2-login.css": {
            "content": "3737dc79c1f4e03c94f915eabca8f83c",
            "lastUpdate": "2020-06-17T19:08:39.589Z"
        },
        "arquivos/consul2-myorders.css": {
            "content": "a1241ff187068110aac33d11c385fa24",
            "lastUpdate": "2020-06-17T19:08:39.590Z"
        },
        "arquivos/consul2-produto-v2.css": {
            "content": "5df4a9ae2afbf9eff19b6490e6e12f83",
            "lastUpdate": "2020-06-17T19:08:39.592Z"
        },
        "arquivos/consul2-produto.css": {
            "content": "4831f9a8abb9b9f9d4aa4d3f015677c2",
            "lastUpdate": "2020-06-17T19:08:39.594Z"
        },
        "arquivos/consul2-shared.css": {
            "content": "0858f28011a3f548f3ca6aaa1a254ad6",
            "lastUpdate": "2020-06-17T19:08:39.595Z"
        },
        "arquivos/consul2-style.css": {
            "content": "7a0b5573e083675f633a8f9aeec586df",
            "lastUpdate": "2020-06-17T19:08:39.597Z"
        },
        "arquivos/consulcoheadline_std_bd-webfont.eot.css": {
            "content": "13b2a15696384e6546d1ebc17469be29",
            "lastUpdate": "2020-06-15T20:07:53.133Z"
        },
        "arquivos/consulcoheadline_std_bd-webfont.svg.css": {
            "content": "16d773b2abf55348648e124557d1b876",
            "lastUpdate": "2020-06-17T19:08:39.597Z"
        },
        "arquivos/consulcoheadline_std_bd-webfont.ttf.css": {
            "content": "5d20b3bf4856b474497772b93ca5edd4",
            "lastUpdate": "2020-06-15T20:07:53.134Z"
        },
        "arquivos/consulcoheadline_std_bd-webfont.woff.css": {
            "content": "a24fb1d6623e1a879bd6ce2410f8620c",
            "lastUpdate": "2020-06-15T20:07:53.135Z"
        },
        "arquivos/consulcoheadline_std_bd-webfont.woff2.css": {
            "content": "ebd6a9b6e9f949cea33b3765464afcc1",
            "lastUpdate": "2020-06-15T20:07:53.135Z"
        },
        "arquivos/consulcoheadline_std_lt-webfont.eot.css": {
            "content": "1d3accb3c60bf790aa55c45635d7ff5b",
            "lastUpdate": "2020-06-15T20:07:53.136Z"
        },
        "arquivos/consulcoheadline_std_lt-webfont.svg.css": {
            "content": "d6bb27df6e91e2f28aa165b3bc69a2ad",
            "lastUpdate": "2020-06-17T19:08:39.598Z"
        },
        "arquivos/consulcoheadline_std_lt-webfont.ttf.css": {
            "content": "0b5ea22ef1f79c158550b50e688ba445",
            "lastUpdate": "2020-06-15T20:07:53.137Z"
        },
        "arquivos/consulcoheadline_std_lt-webfont.woff.css": {
            "content": "bef9063956e6c10b072ee6d8c97281b6",
            "lastUpdate": "2020-06-15T20:07:53.137Z"
        },
        "arquivos/consulcoheadline_std_lt-webfont.woff2.css": {
            "content": "9917e5cbf336138d8aa0bfe3f364be5e",
            "lastUpdate": "2020-06-15T20:07:53.138Z"
        },
        "arquivos/consulcoheadline_std_rg-webfont.eot.css": {
            "content": "94a294365dcb7cbe4e1c54b39e384091",
            "lastUpdate": "2020-06-15T20:07:53.139Z"
        },
        "arquivos/consulcoheadline_std_rg-webfont.svg.css": {
            "content": "82a968dd5198f07106292c33ac28cb43",
            "lastUpdate": "2020-06-17T19:08:39.599Z"
        },
        "arquivos/consulcoheadline_std_rg-webfont.ttf.css": {
            "content": "b630c09e3ee56c6a0d05fa6bc4889b02",
            "lastUpdate": "2020-06-15T20:07:53.140Z"
        },
        "arquivos/consulcoheadline_std_rg-webfont.woff.css": {
            "content": "9bb77b94b823cbe8fbe3b7899d297e28",
            "lastUpdate": "2020-06-15T20:07:53.140Z"
        },
        "arquivos/consulcoheadline_std_rg-webfont.woff2.css": {
            "content": "179f798eb0d872074c48067d047f3dd5",
            "lastUpdate": "2020-06-15T20:07:53.141Z"
        },
        "arquivos/whirlpool2.eot.css": {
            "content": "af1e9544d9a341d4b882d3e6b9534fdc",
            "lastUpdate": "2020-06-15T20:07:53.141Z"
        },
        "arquivos/whirlpool2.svg.css": {
            "content": "e9c289347bedbf61f2905f709f8213ce",
            "lastUpdate": "2020-06-17T19:08:39.600Z"
        },
        "arquivos/whirlpool2.ttf.css": {
            "content": "e7639a56979c74776fa35cd1bdc03968",
            "lastUpdate": "2020-06-15T20:07:53.143Z"
        },
        "arquivos/whirlpool2.woff.css": {
            "content": "3af078c9908279729c57b8ccf0fcb140",
            "lastUpdate": "2020-06-15T20:07:53.143Z"
        },
        "arquivos/whirlpool2.woff2.css": {
            "content": "e122b1e5d3abd6c496bdac0129e700df",
            "lastUpdate": "2020-06-15T20:07:53.144Z"
        },
        "0-consul-footer-2019-after": {
            "content": "1061e59eb5cb0472159aac3f78471c75",
            "lastUpdate": "2020-06-17T19:08:41.584Z"
        },
        "0-consul-footer-2019-atendimento": {
            "content": "30ca05bc400f2e4e231325d8dbef6b03",
            "lastUpdate": "2020-06-17T19:08:41.590Z"
        },
        "0-consul-footer-2019-bottom": {
            "content": "d87dc42cdaa8c48d1b4d701c453f5e63",
            "lastUpdate": "2020-06-17T19:08:41.591Z"
        },
        "0-consul-footer-2019-menu": {
            "content": "4d8fa34c1ebb24cc935574ca5717fd0a",
            "lastUpdate": "2020-06-17T19:08:41.592Z"
        },
        "0-consul-footer-2019-newsletter": {
            "content": "724ed62440e66a50cc5fa41806d6f06f",
            "lastUpdate": "2020-06-17T19:08:41.593Z"
        },
        "0-consul-footer-2019-servicos": {
            "content": "548bae378635b12316b0665767798abe",
            "lastUpdate": "2020-06-17T19:08:41.593Z"
        },
        "0-consul-footer": {
            "content": "fa36ad266a33eac5c28937f63f86c34a",
            "lastUpdate": "2020-06-17T19:08:41.594Z"
        },
        "0-consul-head-content": {
            "content": "4b6c4f0255eebf770fa0ffcc6ab25352",
            "lastUpdate": "2020-06-17T19:08:41.595Z"
        },
        "0-consul-header-landing-aniversario": {
            "content": "b605c29ece28588a116ee650ae4fef77",
            "lastUpdate": "2020-06-17T19:08:41.595Z"
        },
        "0-consul-header-old": {
            "content": "724623c9ee62b7af4151d79bb1d83f4f",
            "lastUpdate": "2020-06-17T19:08:41.596Z"
        },
        "0-consul-header": {
            "content": "89144e5cb446288264e8af7ef5da9767",
            "lastUpdate": "2020-06-17T19:08:41.596Z"
        },
        "0-consul-servicos": {
            "content": "501c96104212722c032075c165a23b35",
            "lastUpdate": "2020-06-17T19:08:41.597Z"
        },
        "0-consul-top-header": {
            "content": "900a4fed2bdace5f6e3f7cc4723dfe6a",
            "lastUpdate": "2020-06-17T19:08:41.597Z"
        },
        "files/checkout-confirmation-custom.js": {
            "content": "54646c525edfe5d0fcadc96b53490d8d",
            "lastUpdate": "2020-06-17T19:08:35.641Z"
        },
        "files/checkout5-custom.js": {
            "content": "a9433161be5f8c5fcd57aa2455d1ba15",
            "lastUpdate": "2020-06-17T19:08:35.644Z"
        },
        "arquivos/checkout-confirmation-custom.min.js": {
            "content": "54646c525edfe5d0fcadc96b53490d8d",
            "lastUpdate": "2020-06-17T19:08:39.570Z"
        },
        "arquivos/checkout5-custom.min.js": {
            "content": "a9433161be5f8c5fcd57aa2455d1ba15",
            "lastUpdate": "2020-06-17T19:08:39.578Z"
        },
        "arquivos/consul2-app.min.js": {
            "content": "b32b4a15e442e6d0ac7c5b1172d3efdf",
            "lastUpdate": "2020-06-17T19:08:39.580Z"
        },
        "arquivos/consul2-cervejeiras.min.js": {
            "content": "6ec2b842fd5b97f9e3d885d71c12181c",
            "lastUpdate": "2020-06-17T19:08:39.581Z"
        },
        "arquivos/consul2-cta.min.js": {
            "content": "bcb3fe5a5f8f26985cf9c3de899a0763",
            "lastUpdate": "2020-06-17T19:08:39.582Z"
        },
        "arquivos/consul2-home.min.js": {
            "content": "b3762dbbea87aadb3cd10253167abedb",
            "lastUpdate": "2020-06-17T19:08:39.585Z"
        },
        "arquivos/consul2-linha-embutir.min.js": {
            "content": "4d87fc18ddeb18c3795aae9e3041b91c",
            "lastUpdate": "2020-06-17T19:08:39.586Z"
        },
        "arquivos/consul2-listagem-embutidos.min.js": {
            "content": "4d64503b3cf8087aaba99c653d8bf3d7",
            "lastUpdate": "2020-06-17T19:08:39.587Z"
        },
        "arquivos/consul2-listagem.min.js": {
            "content": "e06f626b8d082cc4a8abeef5765696f3",
            "lastUpdate": "2020-06-17T19:08:39.589Z"
        },
        "arquivos/consul2-myorders.min.js": {
            "content": "539525ea0b4ad56780bc9abd0256875e",
            "lastUpdate": "2020-06-17T19:08:39.592Z"
        },
        "arquivos/consul2-produto-v2.min.js": {
            "content": "0d71fd719b811630ea36f18bb32594d2",
            "lastUpdate": "2020-06-17T19:08:39.594Z"
        },
        "arquivos/consul2-produto.min.js": {
            "content": "4593495d5f393e63e76bc6daecbc9a19",
            "lastUpdate": "2020-06-17T19:08:39.595Z"
        },
        "arquivos/consul2-shared.min.js": {
            "content": "b4f4dbd20813436fac12239774b284be",
            "lastUpdate": "2020-06-17T19:08:39.596Z"
        },
        "0-consul-busca-chaordic": {
            "content": "985e3f6d04cfbafa6ac03fbc18c7c7af",
            "lastUpdate": "2020-06-17T19:08:44.510Z"
        },
        "0-consul-busca-chaordic2": {
            "content": "a0d7b9b2db805422b2e28a67470871eb",
            "lastUpdate": "2020-06-17T19:08:44.516Z"
        },
        "0-consul-busca": {
            "content": "7b0d7951dd48ab9a64044f8d2853031e",
            "lastUpdate": "2020-06-17T19:08:44.517Z"
        },
        "0-consul-calculadora-btu": {
            "content": "1a0dd5c4aaaf383cd3160e63fe100a50",
            "lastUpdate": "2020-06-17T19:08:44.518Z"
        },
        "0-consul-consumer-week": {
            "content": "0d8d1f5ec64be9c4c6cdc420f10aa66b",
            "lastUpdate": "2020-06-17T19:08:44.519Z"
        },
        "0-consul-cta": {
            "content": "7fe2f658f8ead934dfcf113cb381883d",
            "lastUpdate": "2020-06-17T19:08:44.519Z"
        },
        "0-consul-home-BF-2019": {
            "content": "4386abbfdd342044d91984ffa7cf1b87",
            "lastUpdate": "2020-06-17T19:08:44.521Z"
        },
        "0-consul-home-chaordic": {
            "content": "30e3733249c292cfc8118b6b1a5bc681",
            "lastUpdate": "2020-06-17T19:08:44.521Z"
        },
        "0-consul-home-pj": {
            "content": "51d037b020c485f061b954638cd6e58f",
            "lastUpdate": "2020-06-17T19:08:44.522Z"
        },
        "0-consul-home": {
            "content": "5ecb36fb2646dbbe9859d70211f13cd7",
            "lastUpdate": "2020-06-17T19:08:44.523Z"
        },
        "0-consul-institucional": {
            "content": "625846c95ceb22a6aaafe8dcb965515f",
            "lastUpdate": "2020-06-17T19:08:44.523Z"
        },
        "0-consul-landing-covid": {
            "content": "cadb17a417851cb39bb0c85f992aff2f",
            "lastUpdate": "2020-06-17T19:08:44.524Z"
        },
        "0-consul-landing-cwh14ab": {
            "content": "bc8c9f4921aa404cdef95ea118ef5898",
            "lastUpdate": "2020-06-17T19:08:44.525Z"
        },
        "0-consul-landing-novos-bebedouros": {
            "content": "9d76b78b0798b8123aec0e83353e7165",
            "lastUpdate": "2020-06-17T19:08:44.526Z"
        },
        "0-consul-linha-embutir": {
            "content": "47d7ee4fe566dd49763d040b8167a7dd",
            "lastUpdate": "2020-06-17T19:08:44.527Z"
        },
        "0-consul-listagem-ar-condicionado": {
            "content": "fffdba7504b8532f4e71ca2eced496d9",
            "lastUpdate": "2020-06-17T19:08:44.529Z"
        },
        "0-consul-listagem-embutidos": {
            "content": "ac2b0ae3b3a865a7e0a9a06a6eaae319",
            "lastUpdate": "2020-06-17T19:08:44.535Z"
        },
        "0-consul-listagem-smartbeer-2": {
            "content": "dd5ce6fc419569fef79adbd6a14be3c7",
            "lastUpdate": "2020-06-17T19:08:44.536Z"
        },
        "0-consul-listagem": {
            "content": "4bc9c41c3cd15b4505257530c86bfcf2",
            "lastUpdate": "2020-06-17T19:08:44.538Z"
        },
        "0-consul-login": {
            "content": "8322483245d93d0b11369c55e90b3a28",
            "lastUpdate": "2020-06-17T19:08:44.539Z"
        },
        "0-consul-meuspedidos": {
            "content": "6ed65bc84c2609eafaff060adb8f5cf8",
            "lastUpdate": "2020-06-17T19:08:44.540Z"
        },
        "0-consul-minhaconta": {
            "content": "adec1a8c921d8d211e7220938b707d04",
            "lastUpdate": "2020-06-17T19:08:44.541Z"
        },
        "0-consul-minicart": {
            "content": "4b83a650c3f31ef7464a9549c838a23b",
            "lastUpdate": "2020-06-17T19:08:44.542Z"
        },
        "0-consul-navegacao-categoria-antigo-home": {
            "content": "8f00b1dc736b7faf9d70045222826828",
            "lastUpdate": "2020-06-17T19:08:44.548Z"
        },
        "0-consul-neemu": {
            "content": "0fa1b532f0f766112185622c08d9ed60",
            "lastUpdate": "2020-06-17T19:08:44.549Z"
        },
        "0-consul-pedidos": {
            "content": "1ffac6bad3ab39c4b7b748caf8de9d3a",
            "lastUpdate": "2020-06-17T19:08:44.552Z"
        },
        "0-consul-produto-kit": {
            "content": "cb6a17357276ca42a9e00542d4ebb571",
            "lastUpdate": "2020-06-17T19:08:44.554Z"
        },
        "0-consul-produto-produtos-adicionais": {
            "content": "3fb8d64f45c89f8d93b5208530b7793f",
            "lastUpdate": "2020-06-17T19:08:44.555Z"
        },
        "0-consul-produto-quiz": {
            "content": "657697bf63ccd5024fe200ac8e7744d6",
            "lastUpdate": "2020-06-17T19:08:44.556Z"
        },
        "0-consul-produto-refri": {
            "content": "ef322c7310f6b0d914ca2252613015fb",
            "lastUpdate": "2020-06-17T19:08:44.557Z"
        },
        "0-consul-produto-v2": {
            "content": "fc78da19d92dd6813cd17e794a5bcc9e",
            "lastUpdate": "2020-06-17T19:08:44.558Z"
        },
        "0-consul-produto": {
            "content": "762cc7047a93c3bc91a45187dbea362a",
            "lastUpdate": "2020-06-17T19:08:44.558Z"
        },
        "0-consul-destaque": {
            "content": "1890024d01bfdeb4a96c7b14c8bb005b",
            "lastUpdate": "2020-06-17T19:08:47.316Z"
        },
        "0-consul-prateleira-compre-junto": {
            "content": "9a2e8a7ce9a3c21e45d24e72fb295a2c",
            "lastUpdate": "2020-06-17T19:08:47.319Z"
        },
        "0-consul-prateleira-default": {
            "content": "ffbe56f7cc5b7d21b996acdfdf4592bc",
            "lastUpdate": "2020-06-17T19:08:47.319Z"
        },
        "0-consul-prateleira-personalizada": {
            "content": "11b4a4cb3c75fb52ed26ada60da2deec",
            "lastUpdate": "2020-06-17T19:08:47.320Z"
        },
        "0-consul-produto-banner": {
            "content": "6a4bd9eafdb2913a8584eb118f76ff59",
            "lastUpdate": "2020-06-17T19:08:47.321Z"
        },
        "0-consul-smartbeer-shelf": {
            "content": "f80ea46b3eccb98e219f7833e9468583",
            "lastUpdate": "2020-06-17T19:08:47.323Z"
        },
        "0-ga-impressions": {
            "content": "4e6584395e2b59d1257be2301b2c961e",
            "lastUpdate": "2020-06-17T19:08:47.324Z"
        },
        "0-prateleira-default": {
            "content": "0538824a1764e3eb78f039120cc35727",
            "lastUpdate": "2020-06-17T19:08:47.324Z"
        },
        "0-shelf-blackfriday-2018": {
            "content": "f699e489d515182e9b4cadc75948ebed",
            "lastUpdate": "2020-06-17T19:08:47.325Z"
        }
    }
}
