{
    "consul": {
        "files/checkout-confirmation-custom.js": {
            "content": "f931aa4ab6f5a30610a0da54c92cfca1",
            "lastUpdate": "2019-11-28T13:28:04.410Z"
        },
        "files/checkout5-custom.css": {
            "content": "ffefebf44871100b0f0c6fff4f02de73",
            "lastUpdate": "2019-11-28T13:28:04.412Z"
        },
        "files/checkout5-custom.js": {
            "content": "154936976495c410b5b86bc3ee0aec17",
            "lastUpdate": "2019-11-28T13:28:04.413Z"
        },
        "arquivos/checkout-confirmation-custom.min.js": {
            "content": "f931aa4ab6f5a30610a0da54c92cfca1",
            "lastUpdate": "2019-11-28T13:28:10.580Z"
        },
        "arquivos/checkout5-custom.min.js": {
            "content": "154936976495c410b5b86bc3ee0aec17",
            "lastUpdate": "2019-11-28T13:28:10.583Z"
        },
        "arquivos/consul2-app.min.js": {
            "content": "af43a8babb122bf914103c6ae3c8fde5",
            "lastUpdate": "2019-11-28T13:28:10.585Z"
        },
        "arquivos/consul2-cervejeiras.min.js": {
            "content": "d94ab88b1d7856ac88c4702ed038578f",
            "lastUpdate": "2019-11-28T13:28:10.588Z"
        },
        "arquivos/consul2-cta.min.js": {
            "content": "96c673089eb3574f9972053fdb6a4e7f",
            "lastUpdate": "2019-11-28T13:28:10.590Z"
        },
        "arquivos/consul2-home.min.js": {
            "content": "a90a6d64b0e49a82561fdc9f6640ce08",
            "lastUpdate": "2019-11-28T13:28:10.594Z"
        },
        "arquivos/consul2-linha-embutir.min.js": {
            "content": "b45b914f8d88e2baedfa4a0c9baa3900",
            "lastUpdate": "2019-11-28T13:28:10.597Z"
        },
        "arquivos/consul2-listagem-embutidos.min.js": {
            "content": "1fe6ca09af8b2c2e76e29f923f3939e1",
            "lastUpdate": "2019-11-28T13:28:10.599Z"
        },
        "arquivos/consul2-listagem.min.js": {
            "content": "ace656e9d433ddb7ab1c21a8742e4f28",
            "lastUpdate": "2019-11-28T13:28:10.601Z"
        },
        "arquivos/consul2-myorders.min.js": {
            "content": "0fcd621f9ec8de2ed743ed1d2d59a7b6",
            "lastUpdate": "2019-11-28T13:28:10.604Z"
        },
        "arquivos/consul2-produto.min.js": {
            "content": "9ad4dc85314ca5c8071fc93d9f25e4e5",
            "lastUpdate": "2019-11-28T13:28:10.607Z"
        },
        "0-consul-footer-2019-after": {
            "content": "bde60770ca48b009c976f63464e2eb36",
            "lastUpdate": "2019-11-28T13:28:12.064Z"
        },
        "0-consul-footer-2019-atendimento": {
            "content": "534b7381ab8e87f611a67eb13b751afe",
            "lastUpdate": "2019-11-28T13:12:33.325Z"
        },
        "0-consul-footer-2019-bottom": {
            "content": "1ad1aa78effe368b76cfda2dd3d57c74",
            "lastUpdate": "2019-11-06T13:54:34.014Z"
        },
        "0-consul-footer-2019-menu": {
            "content": "9dd11962e0488780255221520ac070de",
            "lastUpdate": "2019-10-25T17:08:04.652Z"
        },
        "0-consul-footer-2019-newsletter": {
            "content": "a7c0fc212ca26f62f6f13d33b235867b",
            "lastUpdate": "2019-10-25T17:08:04.657Z"
        },
        "0-consul-footer-2019-servicos": {
            "content": "319a5846c81cbe49d3bc0a0ff7755a36",
            "lastUpdate": "2019-10-25T17:08:04.661Z"
        },
        "0-consul-footer": {
            "content": "81f62cac237fae882a21220808dec9b2",
            "lastUpdate": "2019-11-28T13:28:12.067Z"
        },
        "0-consul-head-content": {
            "content": "ed8fff30663207c37701a8e2be9f618a",
            "lastUpdate": "2019-11-28T13:28:12.069Z"
        },
        "0-consul-header-landing-aniversario": {
            "content": "1910336e272c9c66e4ca87916135b398",
            "lastUpdate": "2019-11-21T19:33:28.359Z"
        },
        "0-consul-header": {
            "content": "83d171d80e74e6ef7c7e9be1341b766b",
            "lastUpdate": "2019-11-25T19:55:42.496Z"
        },
        "0-consul-servicos": {
            "content": "5ba5fffced30e6f0e60ebc222b6b1ae4",
            "lastUpdate": "2019-10-25T17:08:04.693Z"
        },
        "0-consul-top-header": {
            "content": "37b64caf4e4fe78ca7fb93cd7b6a7b75",
            "lastUpdate": "2019-10-25T17:08:04.698Z"
        },
        "0-consul-busca-chaordic": {
            "content": "8d7dc8102833239da7b3d6c55a19ccf3",
            "lastUpdate": "2019-11-28T13:28:15.220Z"
        },
        "0-consul-busca-chaordic2": {
            "content": "966bcd39e63f422a37de38f3253ebecb",
            "lastUpdate": "2019-11-28T13:28:15.222Z"
        },
        "0-consul-busca": {
            "content": "2cb72e48cb3c56edc60c749a7599a31e",
            "lastUpdate": "2019-11-28T13:28:15.225Z"
        },
        "0-consul-calculadora-btu": {
            "content": "9fba2921638c2425495bd58c79a61a60",
            "lastUpdate": "2019-11-28T13:28:15.227Z"
        },
        "0-consul-cta": {
            "content": "bfd9300262fc852b6c4ba94ad93621d3",
            "lastUpdate": "2019-11-28T13:28:15.230Z"
        },
        "0-consul-home-BF-2019": {
            "content": "a4db8162d0d75cbe002ecace1568001d",
            "lastUpdate": "2019-11-28T13:28:15.232Z"
        },
        "0-consul-home-chaordic": {
            "content": "290133e6cb99daeddbb0a15f0645984e",
            "lastUpdate": "2019-10-25T17:08:07.033Z"
        },
        "0-consul-home-pj": {
            "content": "88999e4c43e02f29ee9f17d377d2b469",
            "lastUpdate": "2019-11-28T13:28:15.235Z"
        },
        "0-consul-home": {
            "content": "0a3b1c00132e7fcf36f8f16da83f718c",
            "lastUpdate": "2019-11-28T13:28:15.239Z"
        },
        "0-consul-institucional": {
            "content": "13729b36c20fcd354b979d4d0f466967",
            "lastUpdate": "2019-11-28T13:28:15.242Z"
        },
        "0-consul-landing-cwh14ab": {
            "content": "0f2c58dc1af4039260ccc23b84059fdf",
            "lastUpdate": "2019-10-25T17:08:07.055Z"
        },
        "0-consul-linha-embutir": {
            "content": "e23b95945e8ce75e0588944910f29610",
            "lastUpdate": "2019-11-28T13:28:15.245Z"
        },
        "0-consul-listagem-ar-condicionado": {
            "content": "72d5444ed6c118bea57deb69ee3b8986",
            "lastUpdate": "2019-11-28T13:28:15.247Z"
        },
        "0-consul-listagem-embutidos": {
            "content": "bd97e6c15c1a5089f00ed4f3ce010a40",
            "lastUpdate": "2019-11-28T13:28:15.249Z"
        },
        "0-consul-listagem-smartbeer-2": {
            "content": "6c7aae974afc82b1cebf4581cd72cec4",
            "lastUpdate": "2019-11-28T13:28:15.251Z"
        },
        "0-consul-listagem": {
            "content": "ae707b08c7d581b10d8d17a4a3c9f1a6",
            "lastUpdate": "2019-11-28T13:28:15.254Z"
        },
        "0-consul-login": {
            "content": "d8f3e809ac834c5c1fdc29e320cc1d9b",
            "lastUpdate": "2019-11-28T13:28:15.258Z"
        },
        "0-consul-meuspedidos": {
            "content": "628420427be952c4b2960cc0fce83c39",
            "lastUpdate": "2019-11-28T13:28:15.261Z"
        },
        "0-consul-minhaconta": {
            "content": "74e4b427108776cbea2008f96ba15f71",
            "lastUpdate": "2019-11-28T13:28:15.263Z"
        },
        "0-consul-minicart": {
            "content": "4b83a650c3f31ef7464a9549c838a23b",
            "lastUpdate": "2019-11-21T19:33:31.197Z"
        },
        "0-consul-neemu": {
            "content": "1236faa18834b2908644ee1e4eb3ba0a",
            "lastUpdate": "2019-11-28T13:28:15.265Z"
        },
        "0-consul-pedidos": {
            "content": "d821f1bef98dda2bc05e4abc5d309655",
            "lastUpdate": "2019-11-28T13:28:15.266Z"
        },
        "0-consul-produto-kit": {
            "content": "926d7be47eec26d6511cfa3b716dd81f",
            "lastUpdate": "2019-11-28T13:28:15.267Z"
        },
        "0-consul-produto-produtos-adicionais": {
            "content": "f309068acb5ce0325e07c6ddcf8364e5",
            "lastUpdate": "2019-11-28T13:28:15.272Z"
        },
        "0-consul-produto-quiz": {
            "content": "a1def9b07b384bed26874cedf697e020",
            "lastUpdate": "2019-11-28T13:28:15.275Z"
        },
        "0-consul-produto-refri": {
            "content": "9c0a060cd2e2ed75772f647e5b885970",
            "lastUpdate": "2019-11-28T13:28:15.279Z"
        },
        "0-consul-produto": {
            "content": "f309068acb5ce0325e07c6ddcf8364e5",
            "lastUpdate": "2019-11-28T13:28:15.280Z"
        },
        "0-consul-destaque": {
            "content": "eff9bc74812a84792144166a6aa4e3a7",
            "lastUpdate": "2019-10-25T17:08:09.591Z"
        },
        "0-consul-prateleira-compre-junto": {
            "content": "47b3943122737d246fdad1067023b6ea",
            "lastUpdate": "2019-10-25T17:08:09.595Z"
        },
        "0-consul-prateleira-default": {
            "content": "8108de2046e2fc6edc2be76c2df6f7c2",
            "lastUpdate": "2019-11-06T12:18:03.122Z"
        },
        "0-consul-prateleira-personalizada": {
            "content": "2f4962eab76e23b9203c88e66519b1e3",
            "lastUpdate": "2019-11-05T21:02:17.585Z"
        },
        "0-consul-produto-banner": {
            "content": "b774639b1cabfda6535ef0045cd8e899",
            "lastUpdate": "2019-10-25T17:08:09.611Z"
        },
        "0-consul-smartbeer-shelf": {
            "content": "313b398b77d43e87d0e1d213c1dc3eb1",
            "lastUpdate": "2019-10-25T17:08:09.617Z"
        },
        "0-ga-impressions": {
            "content": "9b4403097cf746796508ab0c570b399e",
            "lastUpdate": "2019-10-25T17:08:09.623Z"
        },
        "0-prateleira-default": {
            "content": "806e9b43b3d9669e0322ee42bc1fe3b3",
            "lastUpdate": "2019-11-06T12:18:03.134Z"
        },
        "0-shelf-blackfriday-2018": {
            "content": "7c31fe6c4a3b6934544a0c9dd9b8f8be",
            "lastUpdate": "2019-10-25T17:08:09.634Z"
        },
        "arquivos/checkout5-custom.css": {
            "content": "ffefebf44871100b0f0c6fff4f02de73",
            "lastUpdate": "2019-11-28T13:28:10.581Z"
        },
        "arquivos/consul2-account.css": {
            "content": "a478bbea9acfa4f26a64628de1393ec5",
            "lastUpdate": "2019-11-21T19:33:26.739Z"
        },
        "arquivos/consul2-bf-2018.css": {
            "content": "751a8cc5c50c7cb7bf2758f3ee86f514",
            "lastUpdate": "2019-11-21T19:33:26.741Z"
        },
        "arquivos/consul2-bf.css": {
            "content": "136530a7d1157a0604018e63f908a492",
            "lastUpdate": "2019-11-19T17:13:56.560Z"
        },
        "arquivos/consul2-cervejeiras.css": {
            "content": "0958fbf521adac94cab608c1534fcc1a",
            "lastUpdate": "2019-11-21T19:33:26.742Z"
        },
        "arquivos/consul2-coupon.css": {
            "content": "5681d7bc8c2b894d1fbb5e76fcf8a8d7",
            "lastUpdate": "2019-10-25T17:08:38.860Z"
        },
        "arquivos/consul2-fonts.css": {
            "content": "30af80459c5d644a3c0be84fef72246c",
            "lastUpdate": "2019-10-25T17:08:38.866Z"
        },
        "arquivos/consul2-footer-bf2019.css": {
            "content": "1031eff50c0ab6b1157c5e9c435c8ef7",
            "lastUpdate": "2019-10-25T17:08:38.872Z"
        },
        "arquivos/consul2-header-bf2019.css": {
            "content": "c3e69d023c3343608aad176ebbb35b21",
            "lastUpdate": "2019-11-25T19:55:41.073Z"
        },
        "arquivos/consul2-home-bf2019.css": {
            "content": "2af97e09abdab9d84527901301af9512",
            "lastUpdate": "2019-11-28T13:28:10.592Z"
        },
        "arquivos/consul2-home.css": {
            "content": "aa482105216bc2149981a614d73326e5",
            "lastUpdate": "2019-11-28T13:28:10.593Z"
        },
        "arquivos/consul2-icons.css": {
            "content": "ae93c4b15b3cde21bddf23f782563c3a",
            "lastUpdate": "2019-11-18T13:27:13.696Z"
        },
        "arquivos/consul2-institucional.css": {
            "content": "473a47044ebcdb0d7ce9ab520a5ad818",
            "lastUpdate": "2019-11-28T13:28:10.596Z"
        },
        "arquivos/consul2-linha-embutir.css": {
            "content": "b12d00deeef0f4e9e7fdecd5ed1023a7",
            "lastUpdate": "2019-11-21T19:33:26.755Z"
        },
        "arquivos/consul2-listagem-embutidos.css": {
            "content": "5fb8fadc3d2899c872f3a504a51af852",
            "lastUpdate": "2019-11-21T19:33:26.760Z"
        },
        "arquivos/consul2-listagem.css": {
            "content": "5fb21264cc39b12c3cd0e934e8d96a16",
            "lastUpdate": "2019-11-28T13:28:10.600Z"
        },
        "arquivos/consul2-login.css": {
            "content": "2f46af2721aa74195aa0ca396d2cc2e6",
            "lastUpdate": "2019-11-28T13:28:10.603Z"
        },
        "arquivos/consul2-myorders.css": {
            "content": "7254f43b34f0ecfa80e792f6bde46d56",
            "lastUpdate": "2019-11-21T19:33:26.772Z"
        },
        "arquivos/consul2-produto.css": {
            "content": "2f81ae2f097fe0392baa27eebfc1bc34",
            "lastUpdate": "2019-11-28T13:28:10.606Z"
        },
        "arquivos/consul2-style.css": {
            "content": "947517f08d3d7eae50bb172a385e5eaa",
            "lastUpdate": "2019-11-28T13:28:10.609Z"
        },
        "arquivos/consul-icons.svg.css": {
            "content": "d41d8cd98f00b204e9800998ecf8427e",
            "lastUpdate": "2019-10-29T13:55:15.476Z"
        },
        "arquivos/consulcoheadline_std_bd-webfont.eot.css": {
            "content": "13b2a15696384e6546d1ebc17469be29",
            "lastUpdate": "2019-10-29T13:55:15.510Z"
        },
        "arquivos/consulcoheadline_std_bd-webfont.svg.css": {
            "content": "7c1edfcd005b803656a6ce5771639655",
            "lastUpdate": "2019-10-29T13:55:15.512Z"
        },
        "arquivos/consulcoheadline_std_bd-webfont.ttf.css": {
            "content": "5d20b3bf4856b474497772b93ca5edd4",
            "lastUpdate": "2019-10-29T13:55:15.516Z"
        },
        "arquivos/consulcoheadline_std_bd-webfont.woff.css": {
            "content": "a24fb1d6623e1a879bd6ce2410f8620c",
            "lastUpdate": "2019-10-29T13:55:15.520Z"
        },
        "arquivos/consulcoheadline_std_bd-webfont.woff2.css": {
            "content": "ebd6a9b6e9f949cea33b3765464afcc1",
            "lastUpdate": "2019-10-29T13:55:15.521Z"
        },
        "arquivos/consulcoheadline_std_lt-webfont.eot.css": {
            "content": "1d3accb3c60bf790aa55c45635d7ff5b",
            "lastUpdate": "2019-10-29T13:55:15.523Z"
        },
        "arquivos/consulcoheadline_std_lt-webfont.svg.css": {
            "content": "9310afe71921eccdec8f1c2295a40d6a",
            "lastUpdate": "2019-10-29T13:55:15.528Z"
        },
        "arquivos/consulcoheadline_std_lt-webfont.ttf.css": {
            "content": "0b5ea22ef1f79c158550b50e688ba445",
            "lastUpdate": "2019-10-29T13:55:15.529Z"
        },
        "arquivos/consulcoheadline_std_lt-webfont.woff.css": {
            "content": "bef9063956e6c10b072ee6d8c97281b6",
            "lastUpdate": "2019-10-29T13:55:15.530Z"
        },
        "arquivos/consulcoheadline_std_lt-webfont.woff2.css": {
            "content": "9917e5cbf336138d8aa0bfe3f364be5e",
            "lastUpdate": "2019-10-29T13:55:15.532Z"
        },
        "arquivos/consulcoheadline_std_rg-webfont.eot.css": {
            "content": "94a294365dcb7cbe4e1c54b39e384091",
            "lastUpdate": "2019-10-29T13:55:15.533Z"
        },
        "arquivos/consulcoheadline_std_rg-webfont.svg.css": {
            "content": "929f9f03b1b8023348e5990709d61a25",
            "lastUpdate": "2019-10-29T13:55:15.534Z"
        },
        "arquivos/consulcoheadline_std_rg-webfont.ttf.css": {
            "content": "b630c09e3ee56c6a0d05fa6bc4889b02",
            "lastUpdate": "2019-10-29T13:55:15.535Z"
        },
        "arquivos/consulcoheadline_std_rg-webfont.woff.css": {
            "content": "9bb77b94b823cbe8fbe3b7899d297e28",
            "lastUpdate": "2019-10-29T13:55:15.536Z"
        },
        "arquivos/consulcoheadline_std_rg-webfont.woff2.css": {
            "content": "179f798eb0d872074c48067d047f3dd5",
            "lastUpdate": "2019-10-29T13:55:15.537Z"
        },
        "arquivos/whirlpool2.eot.css": {
            "content": "af1e9544d9a341d4b882d3e6b9534fdc",
            "lastUpdate": "2019-10-29T13:55:15.538Z"
        },
        "arquivos/whirlpool2.svg.css": {
            "content": "f338b6a98422f3bca293f6aa1e6a3da5",
            "lastUpdate": "2019-10-29T13:55:15.540Z"
        },
        "arquivos/whirlpool2.ttf.css": {
            "content": "e7639a56979c74776fa35cd1bdc03968",
            "lastUpdate": "2019-10-29T13:55:15.541Z"
        },
        "arquivos/whirlpool2.woff.css": {
            "content": "3af078c9908279729c57b8ccf0fcb140",
            "lastUpdate": "2019-10-29T13:55:15.543Z"
        },
        "arquivos/whirlpool2.woff2.css": {
            "content": "e122b1e5d3abd6c496bdac0129e700df",
            "lastUpdate": "2019-10-29T13:55:15.546Z"
        }
    }
}
